{
  "id": "41",
  "version": 0,
  "duration": 2.45,
  "fadeIn": false,
  "tracks": [
    {
      "desc": null,
      "clips": [
        {
          "$type": "miHoYo.HYG.Performance.PTAnimationClip, Assembly-CSharp",
          "actorName": "莫白",
          "animKey": "e3858ff0-b193-442a-a19d-1b99c74beff0",
          "keepLoop": false,
          "name": "动作Clip",
          "_startPoint": 0.0,
          "_duration": 0.450000018
        },
        {
          "$type": "miHoYo.HYG.Performance.PTAnimationClip, Assembly-CSharp",
          "actorName": "莫白",
          "animKey": "9f26f80b-a747-4383-bc13-138f0a71ab0b",
          "keepLoop": true,
          "name": "动作Clip",
          "_startPoint": 0.45,
          "_duration": 2.0
        }
      ],
      "sourceType": 0
    },
    {
      "desc": null,
      "clips": [],
      "sourceType": 0
    }
  ]
}