[
  {
    "textid": "Performance_21010030208_21_6316_fakeName",
    "content": null,
    "info": "闲聊-关于玩家喜好闲聊-动画-1003乐福_选项闲聊"
  },
  {
    "textid": "Performance_21010030208_21_6316_content",
    "content": "世界的风……\n比如并非是让人惊喜的意外，\n是让我们清醒于狂热之事的意外。",
    "info": "闲聊-关于玩家喜好闲聊-动画-1003乐福_选项闲聊"
  },
  {
    "textid": "Performance_21010030208_21_6317_fakeName",
    "content": null,
    "info": "闲聊-关于玩家喜好闲聊-动画-1003乐福_选项闲聊"
  },
  {
    "textid": "Performance_21010030208_21_6317_content",
    "content": "{打哈欠}向我们吹来。\n{惊醒！}啊，抱歉！\n我正在想起某个动漫中的台词。",
    "info": "闲聊-关于玩家喜好闲聊-动画-1003乐福_选项闲聊"
  },
  {
    "textid": "Performance_21010030208_21_6318_fakeName",
    "content": null,
    "info": "闲聊-关于玩家喜好闲聊-动画-1003乐福_选项闲聊"
  },
  {
    "textid": "Performance_21010030208_21_6318_content",
    "content": "是一个关于运气很好的同行，\n意外越狱然后被高额通缉的故事……\n对了，你平时有爱看的动画吗？",
    "info": "闲聊-关于玩家喜好闲聊-动画-1003乐福_选项闲聊"
  },
  {
    "textid": "Performance_21010030208_22_6319_content",
    "content": "奇幻",
    "info": "闲聊-关于玩家喜好闲聊-动画-1003乐福_选项闲聊"
  },
  {
    "textid": "Performance_21010030208_22_6320_content",
    "content": "科幻",
    "info": "闲聊-关于玩家喜好闲聊-动画-1003乐福_选项闲聊"
  },
  {
    "textid": "Performance_21010030208_22_6321_content",
    "content": "青春校园",
    "info": "闲聊-关于玩家喜好闲聊-动画-1003乐福_选项闲聊"
  },
  {
    "textid": "Performance_21010030208_22_6322_content",
    "content": "几乎不看动画",
    "info": "闲聊-关于玩家喜好闲聊-动画-1003乐福_选项闲聊"
  },
  {
    "textid": "Performance_21010030208_23_6323_fakeName",
    "content": null,
    "info": "闲聊-关于玩家喜好闲聊-动画-1003乐福_选项闲聊"
  },
  {
    "textid": "Performance_21010030208_23_6323_content",
    "content": "原来爱好是奇幻的类型，\n那你一定听说过《一络之下》吧，\n是关于，络米像超能力一样的故事！",
    "info": "闲聊-关于玩家喜好闲聊-动画-1003乐福_选项闲聊"
  },
  {
    "textid": "Performance_21010030208_23_6324_fakeName",
    "content": null,
    "info": "闲聊-关于玩家喜好闲聊-动画-1003乐福_选项闲聊"
  },
  {
    "textid": "Performance_21010030208_23_6324_content",
    "content": "就是从那个动画开始，\n我对这个世界上的某个东方航路，\n产生了很大的向往……",
    "info": "闲聊-关于玩家喜好闲聊-动画-1003乐福_选项闲聊"
  },
  {
    "textid": "Performance_21010030208_23_6325_fakeName",
    "content": null,
    "info": "闲聊-关于玩家喜好闲聊-动画-1003乐福_选项闲聊"
  },
  {
    "textid": "Performance_21010030208_23_6325_content",
    "content": "还为此浪费了很多络米\n来试试让自己在天空河上飞行……\n可惜，本来可以用来购买更多《一络之下》。",
    "info": "闲聊-关于玩家喜好闲聊-动画-1003乐福_选项闲聊"
  },
  {
    "textid": "Performance_21010030208_24_6326_fakeName",
    "content": null,
    "info": "闲聊-关于玩家喜好闲聊-动画-1003乐福_选项闲聊"
  },
  {
    "textid": "Performance_21010030208_24_6326_content",
    "content": "是现在热门的科幻类型！\n自从连接世界泡的新浪潮时代开启后，\n这个题材就在宇宙间流行开了！",
    "info": "闲聊-关于玩家喜好闲聊-动画-1003乐福_选项闲聊"
  },
  {
    "textid": "Performance_21010030208_24_6327_fakeName",
    "content": null,
    "info": "闲聊-关于玩家喜好闲聊-动画-1003乐福_选项闲聊"
  },
  {
    "textid": "Performance_21010030208_24_6327_content",
    "content": "咯哈哈哈~咯！\n或许我们现在经历的一切，\n就是某个动画中发生的事。",
    "info": "闲聊-关于玩家喜好闲聊-动画-1003乐福_选项闲聊"
  },
  {
    "textid": "Performance_21010030208_24_6328_fakeName",
    "content": null,
    "info": "闲聊-关于玩家喜好闲聊-动画-1003乐福_选项闲聊"
  },
  {
    "textid": "Performance_21010030208_24_6328_content",
    "content": "也可能，是某个世界的未来，\n是世界之外的未来……\n{惊！}我刚才好像又在说梦话？！",
    "info": "闲聊-关于玩家喜好闲聊-动画-1003乐福_选项闲聊"
  },
  {
    "textid": "Performance_21010030208_25_6329_fakeName",
    "content": null,
    "info": "闲聊-关于玩家喜好闲聊-动画-1003乐福_选项闲聊"
  },
  {
    "textid": "Performance_21010030208_25_6329_content",
    "content": "咯哈哈~咯！是关于青春的动画！\n如果说，看动画是保持一种初心的话，\n青春的动画，就是寻找初心的坐标吧。",
    "info": "闲聊-关于玩家喜好闲聊-动画-1003乐福_选项闲聊"
  },
  {
    "textid": "Performance_21010030208_25_6330_fakeName",
    "content": null,
    "info": "闲聊-关于玩家喜好闲聊-动画-1003乐福_选项闲聊"
  },
  {
    "textid": "Performance_21010030208_25_6330_content",
    "content": "不过最近的青春校园动画，\n有许多变成了“青春犯罪”的题材，\n这让我很难找到我熟悉的青春味道了。",
    "info": "闲聊-关于玩家喜好闲聊-动画-1003乐福_选项闲聊"
  },
  {
    "textid": "Performance_21010030208_26_6331_fakeName",
    "content": null,
    "info": "闲聊-关于玩家喜好闲聊-动画-1003乐福_选项闲聊"
  },
  {
    "textid": "Performance_21010030208_26_6331_content",
    "content": "不爱看动漫吗？\n也是，现实中的生活，\n带给了你足够的快活吧！",
    "info": "闲聊-关于玩家喜好闲聊-动画-1003乐福_选项闲聊"
  },
  {
    "textid": "Performance_21010030208_26_6332_fakeName",
    "content": null,
    "info": "闲聊-关于玩家喜好闲聊-动画-1003乐福_选项闲聊"
  },
  {
    "textid": "Performance_21010030208_26_6332_content",
    "content": "想象力参与到任何一个世界， \n都会带来满足，\n所以，当下是最真实的，不是么咯哈哈~咯！",
    "info": "闲聊-关于玩家喜好闲聊-动画-1003乐福_选项闲聊"
  },
  {
    "textid": "Performance_21010030208_26_6333_fakeName",
    "content": null,
    "info": "闲聊-关于玩家喜好闲聊-动画-1003乐福_选项闲聊"
  },
  {
    "textid": "Performance_21010030208_26_6333_content",
    "content": "那末，现在最喜欢的，\n是哪种动画呢？",
    "info": "闲聊-关于玩家喜好闲聊-动画-1003乐福_选项闲聊"
  },
  {
    "textid": "Performance_21010030208_27_6334_fakeName",
    "content": null,
    "info": "闲聊-关于玩家喜好闲聊-动画-1003乐福_选项闲聊"
  },
  {
    "textid": "Performance_21010030208_27_6334_content",
    "content": "<color=#d3b037>{Pnickname}</color>！\n你正在世界中游乐吗？",
    "info": "闲聊-关于玩家喜好闲聊-动画-1003乐福_选项闲聊"
  },
  {
    "textid": "Performance_21010030208_27_6335_fakeName",
    "content": null,
    "info": "闲聊-关于玩家喜好闲聊-动画-1003乐福_选项闲聊"
  },
  {
    "textid": "Performance_21010030208_27_6335_content",
    "content": "上次我们聊到，\n你喜欢在<color=#8AAB4B>{喜欢的动画}</color>游乐，\n还有印象吗？",
    "info": "闲聊-关于玩家喜好闲聊-动画-1003乐福_选项闲聊"
  },
  {
    "textid": "Performance_21010030208_28_6336_content",
    "content": "是的，我现在也享受着那个世界",
    "info": "闲聊-关于玩家喜好闲聊-动画-1003乐福_选项闲聊"
  },
  {
    "textid": "Performance_21010030208_28_6337_content",
    "content": "不是的，我已经不在那里了",
    "info": "闲聊-关于玩家喜好闲聊-动画-1003乐福_选项闲聊"
  },
  {
    "textid": "Performance_21010030208_29_6338_fakeName",
    "content": null,
    "info": "闲聊-关于玩家喜好闲聊-动画-1003乐福_选项闲聊"
  },
  {
    "textid": "Performance_21010030208_29_6338_content",
    "content": "咯哈哈哈~咯！我也是，\n虽然游世的生活常常给我带来足够的乐趣，",
    "info": "闲聊-关于玩家喜好闲聊-动画-1003乐福_选项闲聊"
  },
  {
    "textid": "Performance_21010030208_29_6339_fakeName",
    "content": null,
    "info": "闲聊-关于玩家喜好闲聊-动画-1003乐福_选项闲聊"
  },
  {
    "textid": "Performance_21010030208_29_6339_content",
    "content": "但是说到底，动画中的世界总是，\n像雷电一样噼里啪啦，\n击打着我耳朵上的灵感！",
    "info": "闲聊-关于玩家喜好闲聊-动画-1003乐福_选项闲聊"
  },
  {
    "textid": "Performance_21010030208_29_6340_fakeName",
    "content": null,
    "info": "闲聊-关于玩家喜好闲聊-动画-1003乐福_选项闲聊"
  },
  {
    "textid": "Performance_21010030208_29_6340_content",
    "content": "我想，这是想象力加持的缘故！\n{打哈欠}或者，也可能是看太晚了，\n结果没休息好的结果",
    "info": "闲聊-关于玩家喜好闲聊-动画-1003乐福_选项闲聊"
  },
  {
    "textid": "Performance_21010030208_30_6341_fakeName",
    "content": null,
    "info": "闲聊-关于玩家喜好闲聊-动画-1003乐福_选项闲聊"
  },
  {
    "textid": "Performance_21010030208_30_6341_content",
    "content": "是现实的世界占据了你快活的时光吗？\n还是说，那个世界，\n已经将它的大门关闭咯。",
    "info": "闲聊-关于玩家喜好闲聊-动画-1003乐福_选项闲聊"
  },
  {
    "textid": "Performance_21010030208_30_6342_fakeName",
    "content": null,
    "info": "闲聊-关于玩家喜好闲聊-动画-1003乐福_选项闲聊"
  },
  {
    "textid": "Performance_21010030208_30_6342_content",
    "content": "还是说，\n其实，你只是换了一个，\n更喜欢的动画世界？",
    "info": "闲聊-关于玩家喜好闲聊-动画-1003乐福_选项闲聊"
  },
  {
    "textid": "Performance_21010030208_30_6343_fakeName",
    "content": null,
    "info": "闲聊-关于玩家喜好闲聊-动画-1003乐福_选项闲聊"
  },
  {
    "textid": "Performance_21010030208_30_6343_content",
    "content": "咯哈哈哈~咯，不论身处何地，\n世界之大，姑且一往，\n既去之，则从之。这是我的信条咯。",
    "info": "闲聊-关于玩家喜好闲聊-动画-1003乐福_选项闲聊"
  },
  {
    "textid": "Performance_21010030208_30_6344_fakeName",
    "content": null,
    "info": "闲聊-关于玩家喜好闲聊-动画-1003乐福_选项闲聊"
  },
  {
    "textid": "Performance_21010030208_30_6344_content",
    "content": "也是我喜欢的《一络之下》的台词。\n所以，不管喜欢哪种动画，\n或是现实中，希望你在那个世界里快活着！",
    "info": "闲聊-关于玩家喜好闲聊-动画-1003乐福_选项闲聊"
  },
  {
    "textid": "Performance_21010030208_31_6345_fakeName",
    "content": null,
    "info": "闲聊-关于玩家喜好闲聊-动画-1003乐福_选项闲聊"
  },
  {
    "textid": "Performance_21010030208_31_6345_content",
    "content": "<color=#d3b037>{Pnickname}</color>，\n上次，你说你不喜欢<color=#8AAB4B>动画</color>，\n现在，也依然是吗？",
    "info": "闲聊-关于玩家喜好闲聊-动画-1003乐福_选项闲聊"
  },
  {
    "textid": "Performance_21010030208_32_6346_content",
    "content": "没错！还是现实世界有意思。",
    "info": "闲聊-关于玩家喜好闲聊-动画-1003乐福_选项闲聊"
  },
  {
    "textid": "Performance_21010030208_32_6347_content",
    "content": "不，我已经有了喜欢的动画。",
    "info": "闲聊-关于玩家喜好闲聊-动画-1003乐福_选项闲聊"
  },
  {
    "textid": "Performance_21010030208_33_6348_fakeName",
    "content": null,
    "info": "闲聊-关于玩家喜好闲聊-动画-1003乐福_选项闲聊"
  },
  {
    "textid": "Performance_21010030208_33_6348_content",
    "content": "咯哈哈哈~咯！\n和我想的一样，毕竟，\n从这里每天微妙的变化中，能感觉到——",
    "info": "闲聊-关于玩家喜好闲聊-动画-1003乐福_选项闲聊"
  },
  {
    "textid": "Performance_21010030208_33_6349_fakeName",
    "content": null,
    "info": "闲聊-关于玩家喜好闲聊-动画-1003乐福_选项闲聊"
  },
  {
    "textid": "Performance_21010030208_33_6349_content",
    "content": "你在默默充实着现实中的生活，\n或许这种，\n是不是可以叫做“现充”？",
    "info": "闲聊-关于玩家喜好闲聊-动画-1003乐福_选项闲聊"
  },
  {
    "textid": "Performance_21010030208_34_6350_fakeName",
    "content": null,
    "info": "闲聊-关于玩家喜好闲聊-动画-1003乐福_选项闲聊"
  },
  {
    "textid": "Performance_21010030208_34_6350_content",
    "content": "咯哈哈哈~咯！看来，\n有了让你沉迷的新世界！\n会是什么呢？",
    "info": "闲聊-关于玩家喜好闲聊-动画-1003乐福_选项闲聊"
  }
]