[
  {
    "textid": "Performance_2000059999_1_textmap_17",
    "content": null,
    "info": "莎莎保底闲聊（待删）_莎莎"
  },
  {
    "textid": "Performance_2000059999_1_textmap_18",
    "content": "莫白说如果有条件，\n以后会建一个新站点，\n这样我就能带大家去各种各样的地方啦！",
    "info": "莎莎保底闲聊（待删）_莎莎"
  },
  {
    "textid": "Performance_2000059999_1_textmap_19",
    "content": null,
    "info": "莎莎保底闲聊（待删）_莎莎"
  },
  {
    "textid": "Performance_2000059999_1_textmap_20",
    "content": "有漫天飞沙的、还有雪花飘飘的、\n甚至有彩色流沙河的世界泡！\n是不是听起来就很好玩？",
    "info": "莎莎保底闲聊（待删）_莎莎"
  },
  {
    "textid": "Performance_2000059999_1_textmap_21",
    "content": null,
    "info": "莎莎保底闲聊（待删）_莎莎"
  },
  {
    "textid": "Performance_2000059999_1_textmap_22",
    "content": "迁风协会的前辈们经常说，\n穿越颠簸乱流虽然麻烦，\n但穿过去之后，会有很多惊喜！",
    "info": "莎莎保底闲聊（待删）_莎莎"
  },
  {
    "textid": "Performance_2000059999_3_textmap_23",
    "content": null,
    "info": "莎莎保底闲聊（待删）_莎莎"
  },
  {
    "textid": "Performance_2000059999_3_textmap_24",
    "content": "对了，再次恭喜你建成新房子！",
    "info": "莎莎保底闲聊（待删）_莎莎"
  },
  {
    "textid": "Performance_2000059999_3_textmap_25",
    "content": null,
    "info": "莎莎保底闲聊（待删）_莎莎"
  },
  {
    "textid": "Performance_2000059999_3_textmap_26",
    "content": "不知不觉，<color=#ca8f50>{me}</color>，\n你已经把自己的生活，\n过得很好了。",
    "info": "莎莎保底闲聊（待删）_莎莎"
  },
  {
    "textid": "Performance_2000059999_3_textmap_27",
    "content": null,
    "info": "莎莎保底闲聊（待删）_莎莎"
  },
  {
    "textid": "Performance_2000059999_3_textmap_28",
    "content": "<size=64>真为你开心！</size>",
    "info": "莎莎保底闲聊（待删）_莎莎"
  },
  {
    "textid": "Performance_2000059999_3_textmap_29",
    "content": null,
    "info": "莎莎保底闲聊（待删）_莎莎"
  },
  {
    "textid": "Performance_2000059999_3_textmap_30",
    "content": "虽然现在没准备什么乔迁礼，\n但如果你想打造更多家具，\n想去更多其他地方的时候……",
    "info": "莎莎保底闲聊（待删）_莎莎"
  },
  {
    "textid": "Performance_2000059999_3_textmap_31",
    "content": null,
    "info": "莎莎保底闲聊（待删）_莎莎"
  },
  {
    "textid": "Performance_2000059999_3_textmap_32",
    "content": "一定记得来找我！\n我正在计划申请建造站点，\n可以期待一下~！",
    "info": "莎莎保底闲聊（待删）_莎莎"
  },
  {
    "textid": "Performance_2000059999_4_textmap_33",
    "content": null,
    "info": "莎莎保底闲聊（待删）_莎莎"
  },
  {
    "textid": "Performance_2000059999_4_textmap_34",
    "content": "迁风协会的前辈们，\n最喜欢饭后抱着酒壶围着炉火聊天，\n他们经常说——",
    "info": "莎莎保底闲聊（待删）_莎莎"
  },
  {
    "textid": "Performance_2000059999_4_textmap_35",
    "content": null,
    "info": "莎莎保底闲聊（待删）_莎莎"
  },
  {
    "textid": "Performance_2000059999_4_textmap_36",
    "content": "“风暴造就更强大的航海者。”\n据说越是危险的乱流背后，\n越是充满了稀有的好东西。",
    "info": "莎莎保底闲聊（待删）_莎莎"
  },
  {
    "textid": "Performance_2000059999_4_textmap_37",
    "content": null,
    "info": "莎莎保底闲聊（待删）_莎莎"
  },
  {
    "textid": "Performance_2000059999_4_textmap_38",
    "content": "当然，有乘客的时候，\n我不会故意开车冒险的。",
    "info": "莎莎保底闲聊（待删）_莎莎"
  },
  {
    "textid": "Performance_2000059999_5_textmap_39",
    "content": null,
    "info": "莎莎保底闲聊（待删）_莎莎"
  },
  {
    "textid": "Performance_2000059999_5_textmap_40",
    "content": "嗯？我正在看跳出水面的鱼……\n你知道吗，我们协会有个家伙，\n喝多了，一个人闯进了未知的乱流！",
    "info": "莎莎保底闲聊（待删）_莎莎"
  },
  {
    "textid": "Performance_2000059999_5_textmap_41",
    "content": null,
    "info": "莎莎保底闲聊（待删）_莎莎"
  },
  {
    "textid": "Performance_2000059999_5_textmap_42",
    "content": "大家都为他担心的不得了，\n结果他笑眯眯地回来了！",
    "info": "莎莎保底闲聊（待删）_莎莎"
  },
  {
    "textid": "Performance_2000059999_5_textmap_43",
    "content": null,
    "info": "莎莎保底闲聊（待删）_莎莎"
  },
  {
    "textid": "Performance_2000059999_5_textmap_44",
    "content": "他说他清醒后，\n发现自己被卷到了一个奇怪的地方——\n一个鱼和龙虾都在天上飘的地方！",
    "info": "莎莎保底闲聊（待删）_莎莎"
  },
  {
    "textid": "Performance_2000059999_5_textmap_45",
    "content": null,
    "info": "莎莎保底闲聊（待删）_莎莎"
  },
  {
    "textid": "Performance_2000059999_5_textmap_46",
    "content": "超离奇的！\n我也想有这么刺激的冒险经历～",
    "info": "莎莎保底闲聊（待删）_莎莎"
  }
]