[
  {
    "$type": "Google.Protobuf.Collections.RepeatedField`1[[System.Single, mscorlib]], Assembly-CSharp",
    "$values": [
      0.0,
      0.0,
      0.0,
      0.0,
      0.0,
      0.0,
      0.000403413054,
      0.0009632951,
      8.724616,
      0.0009334137,
      16.2627411,
      0.001015842,
      0.0007592866
    ]
  },
  {
    "$type": "Google.Protobuf.Collections.RepeatedField`1[[System.Single, mscorlib]], Assembly-CSharp",
    "$values": [
      0.0,
      0.0,
      0.0,
      0.0,
      0.0,
      0.0,
      0.0005525723,
      0.00157051091,
      13.0659523,
      0.0014713034,
      32.7489,
      0.00186244794,
      0.00248781173
    ]
  },
  {
    "$type": "Google.Protobuf.Collections.RepeatedField`1[[System.Single, mscorlib]], Assembly-CSharp",
    "$values": [
      0.0,
      0.0,
      0.0,
      0.0,
      0.0,
      0.0,
      0.00141164393,
      0.002020395,
      13.9929953,
      0.00169375946,
      52.5898132,
      0.0028123532,
      0.0621575676
    ]
  },
  {
    "$type": "Google.Protobuf.Collections.RepeatedField`1[[System.Single, mscorlib]], Assembly-CSharp",
    "$values": [
      0.0,
      0.0,
      0.0,
      0.0,
      0.0,
      0.0,
      0.0025048356,
      0.00247156736,
      23.68911,
      0.00219244044,
      63.6675949,
      0.004043038,
      0.11391148
    ]
  },
  {
    "$type": "Google.Protobuf.Collections.RepeatedField`1[[System.Single, mscorlib]], Assembly-CSharp",
    "$values": [
      0.0,
      0.0,
      0.0,
      0.0,
      0.0,
      0.0,
      0.000937813544,
      0.0009938277,
      78.6067352,
      0.00102691469,
      21.3358479,
      0.001919578,
      0.038719777
    ]
  },
  {
    "$type": "Google.Protobuf.Collections.RepeatedField`1[[System.Single, mscorlib]], Assembly-CSharp",
    "$values": [
      0.0,
      0.0,
      0.0,
      0.0,
      0.0,
      0.0,
      0.0001536072,
      0.000248680357,
      99.92364,
      0.000454295485,
      0.05743167,
      0.0008210426,
      0.00131330849
    ]
  },
  {
    "$type": "Google.Protobuf.Collections.RepeatedField`1[[System.Single, mscorlib]], Assembly-CSharp",
    "$values": [
      0.0,
      0.0,
      0.0,
      0.0,
      0.0,
      0.0,
      0.00505335,
      0.002125216,
      89.2605,
      0.001513044,
      10.5929651,
      0.003562583,
      0.101289555
    ]
  },
  {
    "$type": "Google.Protobuf.Collections.RepeatedField`1[[System.Single, mscorlib]], Assembly-CSharp",
    "$values": [
      0.0,
      0.0,
      0.0,
      0.0,
      0.0,
      0.0,
      0.0313373879,
      0.0109193092,
      71.14145,
      0.00161622267,
      28.5675678,
      0.00777063053,
      0.1857424
    ]
  },
  {
    "$type": "Google.Protobuf.Collections.RepeatedField`1[[System.Single, mscorlib]], Assembly-CSharp",
    "$values": [
      0.0,
      0.0,
      0.0,
      0.0,
      0.0,
      0.0,
      0.050675936,
      0.0311821122,
      68.19297,
      0.00163901516,
      31.4381351,
      0.0124870241,
      0.206094086
    ]
  },
  {
    "$type": "Google.Protobuf.Collections.RepeatedField`1[[System.Single, mscorlib]], Assembly-CSharp",
    "$values": [
      0.0,
      0.0,
      0.0,
      0.0,
      0.0,
      0.0,
      0.9405676,
      0.0542996153,
      67.2073,
      0.00187691371,
      31.4716473,
      0.0191453546,
      0.22058332
    ]
  },
  {
    "$type": "Google.Protobuf.Collections.RepeatedField`1[[System.Single, mscorlib]], Assembly-CSharp",
    "$values": [
      0.0,
      0.0,
      0.0,
      0.0,
      0.0,
      0.0,
      63.03573,
      0.021360958,
      25.9741325,
      0.001745679,
      10.5996761,
      0.0111136017,
      0.136728287
    ]
  },
  {
    "$type": "Google.Protobuf.Collections.RepeatedField`1[[System.Single, mscorlib]], Assembly-CSharp",
    "$values": [
      0.0,
      0.0,
      0.0,
      0.0,
      0.0,
      0.0,
      93.16502,
      0.00332222064,
      6.25100946,
      0.00127676246,
      0.146349072,
      0.00554662151,
      0.08932465
    ]
  },
  {
    "$type": "Google.Protobuf.Collections.RepeatedField`1[[System.Single, mscorlib]], Assembly-CSharp",
    "$values": [
      0.0,
      0.0,
      0.0,
      0.0,
      0.0,
      0.0,
      93.9906158,
      0.003554974,
      5.38059855,
      0.00118777878,
      0.138099417,
      0.005149299,
      0.08739075
    ]
  },
  {
    "$type": "Google.Protobuf.Collections.RepeatedField`1[[System.Single, mscorlib]], Assembly-CSharp",
    "$values": [
      0.0,
      0.0,
      0.0,
      0.0,
      0.0,
      0.0,
      95.0646744,
      0.00557073532,
      4.213314,
      0.00107947853,
      0.138996378,
      0.00473694364,
      0.08592982
    ]
  },
  {
    "$type": "Google.Protobuf.Collections.RepeatedField`1[[System.Single, mscorlib]], Assembly-CSharp",
    "$values": [
      0.0,
      0.0,
      0.0,
      0.0,
      0.0,
      0.0,
      96.12821,
      0.008938756,
      2.96169448,
      0.000961765938,
      0.137235731,
      0.00429673,
      0.08284034
    ]
  },
  {
    "$type": "Google.Protobuf.Collections.RepeatedField`1[[System.Single, mscorlib]], Assembly-CSharp",
    "$values": [
      0.0,
      0.0,
      0.0,
      0.0,
      0.0,
      0.0,
      97.26181,
      0.0133891553,
      1.66338575,
      0.0008566975,
      0.128777564,
      0.00378216058,
      0.07503664
    ]
  },
  {
    "$type": "Google.Protobuf.Collections.RepeatedField`1[[System.Single, mscorlib]], Assembly-CSharp",
    "$values": [
      0.0,
      0.0,
      0.0,
      0.0,
      0.0,
      0.0,
      94.90761,
      0.0303717833,
      0.6677445,
      0.0004870917,
      0.129159868,
      0.00341241388,
      0.07742758
    ]
  },
  {
    "$type": "Google.Protobuf.Collections.RepeatedField`1[[System.Single, mscorlib]], Assembly-CSharp",
    "$values": [
      0.0,
      0.0,
      0.0,
      0.0,
      0.0,
      0.0,
      89.16385,
      0.03808368,
      0.403186619,
      0.000323800021,
      0.133622363,
      0.00334966229,
      0.0807536542
    ]
  },
  {
    "$type": "Google.Protobuf.Collections.RepeatedField`1[[System.Single, mscorlib]], Assembly-CSharp",
    "$values": [
      0.0,
      0.0,
      0.0,
      0.0,
      0.0,
      0.0,
      73.57819,
      0.035120666,
      0.358703852,
      0.000289967953,
      0.120358646,
      0.0029511773,
      0.07036414
    ]
  },
  {
    "$type": "Google.Protobuf.Collections.RepeatedField`1[[System.Single, mscorlib]], Assembly-CSharp",
    "$values": [
      0.0,
      0.0,
      0.0,
      0.0,
      0.0,
      0.0,
      54.0783844,
      0.0275512133,
      0.277124941,
      0.000224169242,
      0.0934337,
      0.00226775347,
      0.0537881926
    ]
  },
  {
    "$type": "Google.Protobuf.Collections.RepeatedField`1[[System.Single, mscorlib]], Assembly-CSharp",
    "$values": [
      0.0,
      0.0,
      0.0,
      0.0,
      0.0,
      0.0,
      34.5785751,
      0.01998176,
      0.195546,
      0.000158370516,
      0.0665087551,
      0.00158432964,
      0.03721225
    ]
  },
  {
    "$type": "Google.Protobuf.Collections.RepeatedField`1[[System.Single, mscorlib]], Assembly-CSharp",
    "$values": [
      0.0,
      0.0,
      0.0,
      0.0,
      0.0,
      0.0,
      15.078763,
      0.0124123069,
      0.113967076,
      9.25718E-05,
      0.03958381,
      0.000900905754,
      0.0206363034
    ]
  },
  {
    "$type": "Google.Protobuf.Collections.RepeatedField`1[[System.Single, mscorlib]], Assembly-CSharp",
    "$values": [
      0.0,
      0.0,
      0.0,
      0.0,
      0.0,
      0.0,
      1.95708013,
      0.00230321917,
      0.0185480826,
      1.59833271E-05,
      0.00683061453,
      0.000142469435,
      0.00309321587
    ]
  },
  {
    "$type": "Google.Protobuf.Collections.RepeatedField`1[[System.Single, mscorlib]], Assembly-CSharp",
    "$values": [
      0.0,
      0.0,
      0.0,
      0.0,
      0.0,
      0.0,
      0.0,
      0.0,
      0.0,
      0.0,
      0.0,
      0.0,
      0.0
    ]
  },
  {
    "$type": "Google.Protobuf.Collections.RepeatedField`1[[System.Single, mscorlib]], Assembly-CSharp",
    "$values": [
      0.0,
      0.0,
      0.0,
      0.0,
      0.0,
      0.0,
      0.0,
      0.0,
      0.0,
      0.0,
      0.0,
      0.0,
      0.0
    ]
  },
  {
    "$type": "Google.Protobuf.Collections.RepeatedField`1[[System.Single, mscorlib]], Assembly-CSharp",
    "$values": [
      0.0,
      0.0,
      0.0,
      0.0,
      0.0,
      0.0,
      0.0,
      0.0,
      0.0,
      0.0,
      0.0,
      0.0,
      0.0
    ]
  },
  {
    "$type": "Google.Protobuf.Collections.RepeatedField`1[[System.Single, mscorlib]], Assembly-CSharp",
    "$values": [
      0.0,
      0.0,
      0.0,
      0.0,
      0.0,
      0.0,
      0.0,
      0.0,
      0.0,
      0.0,
      0.0,
      0.0,
      0.0
    ]
  },
  {
    "$type": "Google.Protobuf.Collections.RepeatedField`1[[System.Single, mscorlib]], Assembly-CSharp",
    "$values": [
      0.0,
      0.0,
      0.0,
      0.0,
      0.0,
      0.0,
      0.0,
      0.0,
      0.0,
      0.0,
      0.0,
      0.0,
      0.0
    ]
  },
  {
    "$type": "Google.Protobuf.Collections.RepeatedField`1[[System.Single, mscorlib]], Assembly-CSharp",
    "$values": [
      0.0,
      0.0,
      0.0,
      0.0,
      0.0,
      0.0,
      0.0,
      0.0,
      0.0,
      0.0,
      0.0,
      0.0,
      0.0
    ]
  },
  {
    "$type": "Google.Protobuf.Collections.RepeatedField`1[[System.Single, mscorlib]], Assembly-CSharp",
    "$values": [
      0.0,
      0.0,
      0.0,
      0.0,
      0.0,
      0.0,
      0.0,
      0.0,
      0.0,
      0.0,
      0.0,
      0.0,
      0.0
    ]
  },
  {
    "$type": "Google.Protobuf.Collections.RepeatedField`1[[System.Single, mscorlib]], Assembly-CSharp",
    "$values": [
      0.0,
      0.0,
      0.0,
      0.0,
      0.0,
      0.0,
      0.0,
      0.0,
      0.0,
      0.0,
      0.0,
      0.0,
      0.0
    ]
  },
  {
    "$type": "Google.Protobuf.Collections.RepeatedField`1[[System.Single, mscorlib]], Assembly-CSharp",
    "$values": [
      0.0,
      0.0,
      0.0,
      0.0,
      0.0,
      0.0,
      0.0,
      0.0,
      0.0,
      0.0,
      0.0,
      0.0,
      0.0
    ]
  },
  {
    "$type": "Google.Protobuf.Collections.RepeatedField`1[[System.Single, mscorlib]], Assembly-CSharp",
    "$values": [
      0.0,
      0.0,
      0.0,
      0.0,
      0.0,
      0.0,
      0.0,
      0.0,
      0.0,
      0.0,
      0.0,
      0.0,
      0.0
    ]
  },
  {
    "$type": "Google.Protobuf.Collections.RepeatedField`1[[System.Single, mscorlib]], Assembly-CSharp",
    "$values": [
      0.0,
      0.0,
      0.0,
      0.0,
      0.0,
      0.0,
      0.0,
      0.0,
      0.0,
      0.0,
      0.0,
      0.0,
      0.0
    ]
  },
  {
    "$type": "Google.Protobuf.Collections.RepeatedField`1[[System.Single, mscorlib]], Assembly-CSharp",
    "$values": [
      0.0,
      0.0,
      0.0,
      0.0,
      0.0,
      0.0,
      0.0,
      0.0,
      0.0,
      0.0,
      0.0,
      0.0,
      0.0
    ]
  },
  {
    "$type": "Google.Protobuf.Collections.RepeatedField`1[[System.Single, mscorlib]], Assembly-CSharp",
    "$values": [
      0.0,
      0.0,
      0.0,
      0.0,
      0.0,
      0.0,
      0.0,
      0.0,
      0.0,
      0.0,
      0.0,
      0.0,
      0.0
    ]
  },
  {
    "$type": "Google.Protobuf.Collections.RepeatedField`1[[System.Single, mscorlib]], Assembly-CSharp",
    "$values": [
      0.0,
      0.0,
      0.0,
      0.0,
      0.0,
      0.0,
      0.0,
      0.0,
      0.0,
      0.0,
      0.0,
      0.0,
      0.0
    ]
  },
  {
    "$type": "Google.Protobuf.Collections.RepeatedField`1[[System.Single, mscorlib]], Assembly-CSharp",
    "$values": [
      0.0,
      0.0,
      0.0,
      0.0,
      0.0,
      0.0,
      0.0,
      0.0,
      0.0,
      0.0,
      0.0,
      0.0,
      0.0
    ]
  },
  {
    "$type": "Google.Protobuf.Collections.RepeatedField`1[[System.Single, mscorlib]], Assembly-CSharp",
    "$values": [
      0.0,
      0.0,
      0.0,
      0.0,
      0.0,
      0.0,
      0.624834538,
      0.0500452444,
      2.55998278,
      0.001970126,
      0.006083446,
      0.045764178,
      0.05075046
    ]
  },
  {
    "$type": "Google.Protobuf.Collections.RepeatedField`1[[System.Single, mscorlib]], Assembly-CSharp",
    "$values": [
      0.0,
      0.0,
      0.0,
      0.0,
      0.0,
      0.0,
      4.312916,
      0.303125471,
      13.9977331,
      0.00972405,
      0.037331678,
      0.272065938,
      0.304238021
    ]
  },
  {
    "$type": "Google.Protobuf.Collections.RepeatedField`1[[System.Single, mscorlib]], Assembly-CSharp",
    "$values": [
      0.0,
      0.0,
      0.0,
      0.0,
      0.0,
      0.0,
      22.0570431,
      2.57412314,
      22.9062843,
      0.007914726,
      0.246842429,
      0.47917676,
      2.01790667
    ]
  },
  {
    "$type": "Google.Protobuf.Collections.RepeatedField`1[[System.Single, mscorlib]], Assembly-CSharp",
    "$values": [
      0.0,
      0.0,
      0.0,
      0.0,
      0.0,
      0.0,
      30.96755,
      3.49910617,
      25.0136642,
      0.004702743,
      0.355809331,
      0.532358646,
      2.77452874
    ]
  },
  {
    "$type": "Google.Protobuf.Collections.RepeatedField`1[[System.Single, mscorlib]], Assembly-CSharp",
    "$values": [
      0.0,
      0.0,
      0.0,
      0.0,
      0.0,
      0.0,
      33.7760925,
      3.15895748,
      25.0122566,
      0.00430448074,
      0.369616032,
      0.5365895,
      2.67469978
    ]
  },
  {
    "$type": "Google.Protobuf.Collections.RepeatedField`1[[System.Single, mscorlib]], Assembly-CSharp",
    "$values": [
      0.0,
      0.0,
      0.0,
      0.0,
      0.0,
      0.0,
      34.131485,
      2.619476,
      21.6408958,
      0.00366551825,
      0.343814462,
      0.468537241,
      2.35545969
    ]
  },
  {
    "$type": "Google.Protobuf.Collections.RepeatedField`1[[System.Single, mscorlib]], Assembly-CSharp",
    "$values": [
      0.0,
      0.0,
      0.0,
      0.0,
      0.0,
      0.0,
      31.432375,
      1.94880736,
      17.0040283,
      0.00288023916,
      0.2926081,
      0.370433331,
      1.87345672
    ]
  },
  {
    "$type": "Google.Protobuf.Collections.RepeatedField`1[[System.Single, mscorlib]], Assembly-CSharp",
    "$values": [
      0.0,
      0.0,
      0.0,
      0.0,
      0.0,
      0.0,
      25.2343616,
      1.19053853,
      11.9222593,
      0.00185833289,
      0.222066283,
      0.2623235,
      1.29128158
    ]
  },
  {
    "$type": "Google.Protobuf.Collections.RepeatedField`1[[System.Single, mscorlib]], Assembly-CSharp",
    "$values": [
      0.0,
      0.0,
      0.0,
      0.0,
      0.0,
      0.0,
      6.96058846,
      0.26941964,
      2.77443957,
      0.000456230016,
      0.05586059,
      0.06212223,
      0.3139434
    ]
  },
  {
    "$type": "Google.Protobuf.Collections.RepeatedField`1[[System.Single, mscorlib]], Assembly-CSharp",
    "$values": [
      0.0,
      0.0,
      0.0,
      0.0,
      0.0,
      0.0,
      0.0,
      0.0,
      0.0,
      0.0,
      0.0,
      0.0,
      0.0
    ]
  },
  {
    "$type": "Google.Protobuf.Collections.RepeatedField`1[[System.Single, mscorlib]], Assembly-CSharp",
    "$values": [
      0.0,
      0.0,
      0.0,
      0.0,
      0.0,
      0.0,
      0.0,
      0.0,
      0.0,
      0.0,
      0.0,
      0.0,
      0.0
    ]
  },
  {
    "$type": "Google.Protobuf.Collections.RepeatedField`1[[System.Single, mscorlib]], Assembly-CSharp",
    "$values": [
      0.0,
      0.0,
      0.0,
      0.0,
      0.0,
      0.0,
      0.0,
      0.0,
      0.0,
      0.0,
      0.0,
      0.0,
      0.0
    ]
  },
  {
    "$type": "Google.Protobuf.Collections.RepeatedField`1[[System.Single, mscorlib]], Assembly-CSharp",
    "$values": [
      0.0,
      0.0,
      0.0,
      0.0,
      0.0,
      0.0,
      0.0,
      0.0,
      0.0,
      0.0,
      0.0,
      0.0,
      0.0
    ]
  },
  {
    "$type": "Google.Protobuf.Collections.RepeatedField`1[[System.Single, mscorlib]], Assembly-CSharp",
    "$values": [
      0.0,
      0.0,
      0.0,
      0.0,
      0.0,
      0.0,
      0.0,
      0.0,
      0.0,
      0.0,
      0.0,
      0.0,
      0.0
    ]
  },
  {
    "$type": "Google.Protobuf.Collections.RepeatedField`1[[System.Single, mscorlib]], Assembly-CSharp",
    "$values": [
      0.0,
      0.0,
      0.0,
      0.0,
      0.0,
      0.0,
      0.0,
      0.0,
      0.0,
      0.0,
      0.0,
      0.0,
      0.0
    ]
  },
  {
    "$type": "Google.Protobuf.Collections.RepeatedField`1[[System.Single, mscorlib]], Assembly-CSharp",
    "$values": [
      0.0,
      0.0,
      0.0,
      0.0,
      0.0,
      0.0,
      0.0,
      0.0,
      0.0,
      0.0,
      0.0,
      0.0,
      0.0
    ]
  },
  {
    "$type": "Google.Protobuf.Collections.RepeatedField`1[[System.Single, mscorlib]], Assembly-CSharp",
    "$values": [
      0.0,
      0.0,
      0.0,
      0.0,
      0.0,
      0.0,
      0.0,
      0.0,
      0.0,
      0.0,
      0.0,
      0.0,
      0.0
    ]
  },
  {
    "$type": "Google.Protobuf.Collections.RepeatedField`1[[System.Single, mscorlib]], Assembly-CSharp",
    "$values": [
      0.0,
      0.0,
      0.0,
      0.0,
      0.0,
      0.0,
      0.0,
      0.0,
      0.0,
      0.0,
      0.0,
      0.0,
      0.0
    ]
  },
  {
    "$type": "Google.Protobuf.Collections.RepeatedField`1[[System.Single, mscorlib]], Assembly-CSharp",
    "$values": [
      0.0,
      0.0,
      0.0,
      0.0,
      0.0,
      0.0,
      0.0,
      0.0,
      0.0,
      0.0,
      0.0,
      0.0,
      0.0
    ]
  },
  {
    "$type": "Google.Protobuf.Collections.RepeatedField`1[[System.Single, mscorlib]], Assembly-CSharp",
    "$values": [
      0.0,
      0.0,
      0.0,
      0.0,
      0.0,
      0.0,
      0.0,
      0.0,
      0.0,
      0.0,
      0.0,
      0.0,
      0.0
    ]
  },
  {
    "$type": "Google.Protobuf.Collections.RepeatedField`1[[System.Single, mscorlib]], Assembly-CSharp",
    "$values": [
      0.0,
      0.0,
      0.0,
      0.0,
      0.0,
      0.0,
      0.0,
      0.0,
      0.0,
      0.0,
      0.0,
      0.0,
      0.0
    ]
  },
  {
    "$type": "Google.Protobuf.Collections.RepeatedField`1[[System.Single, mscorlib]], Assembly-CSharp",
    "$values": [
      0.0,
      0.0,
      0.0,
      0.0,
      0.0,
      0.0,
      0.0,
      0.0,
      0.0,
      0.0,
      0.0,
      0.0,
      0.0
    ]
  },
  {
    "$type": "Google.Protobuf.Collections.RepeatedField`1[[System.Single, mscorlib]], Assembly-CSharp",
    "$values": [
      0.0,
      0.0,
      0.0,
      0.0,
      0.0,
      0.0,
      0.0,
      0.0,
      0.0,
      0.0,
      0.0,
      0.0,
      0.0
    ]
  },
  {
    "$type": "Google.Protobuf.Collections.RepeatedField`1[[System.Single, mscorlib]], Assembly-CSharp",
    "$values": [
      0.0,
      0.0,
      0.0,
      0.0,
      0.0,
      0.0,
      0.0,
      0.0,
      0.0,
      0.0,
      0.0,
      0.0,
      0.0
    ]
  },
  {
    "$type": "Google.Protobuf.Collections.RepeatedField`1[[System.Single, mscorlib]], Assembly-CSharp",
    "$values": [
      0.0,
      0.0,
      0.0,
      0.0,
      0.0,
      0.0,
      0.0,
      0.0,
      0.0,
      0.0,
      0.0,
      0.0,
      0.0
    ]
  },
  {
    "$type": "Google.Protobuf.Collections.RepeatedField`1[[System.Single, mscorlib]], Assembly-CSharp",
    "$values": [
      0.0,
      0.0,
      0.0,
      0.0,
      0.0,
      0.0,
      0.0,
      0.0,
      0.0,
      0.0,
      0.0,
      0.0,
      0.0
    ]
  },
  {
    "$type": "Google.Protobuf.Collections.RepeatedField`1[[System.Single, mscorlib]], Assembly-CSharp",
    "$values": [
      0.0,
      0.0,
      0.0,
      0.0,
      0.0,
      0.0,
      0.0,
      0.0,
      0.0,
      0.0,
      0.0,
      0.0,
      0.0
    ]
  },
  {
    "$type": "Google.Protobuf.Collections.RepeatedField`1[[System.Single, mscorlib]], Assembly-CSharp",
    "$values": [
      0.0,
      0.0,
      0.0,
      0.0,
      0.0,
      0.0,
      2.10185171E-05,
      9.204267E-05,
      0.000202502779,
      3.87405926E-05,
      2.74489157E-05,
      4.1443634,
      0.0204814915
    ]
  },
  {
    "$type": "Google.Protobuf.Collections.RepeatedField`1[[System.Single, mscorlib]], Assembly-CSharp",
    "$values": [
      0.0,
      0.0,
      0.0,
      0.0,
      0.0,
      0.0,
      0.000205872144,
      0.000349333946,
      0.00172434258,
      0.000168357932,
      0.000237478409,
      12.4749336,
      12.5173035
    ]
  },
  {
    "$type": "Google.Protobuf.Collections.RepeatedField`1[[System.Single, mscorlib]], Assembly-CSharp",
    "$values": [
      0.0,
      0.0,
      0.0,
      0.0,
      0.0,
      0.0,
      0.0014550956,
      0.000399125216,
      8.305375,
      0.00029830134,
      0.0005600864,
      12.4765253,
      25.0418015
    ]
  },
  {
    "$type": "Google.Protobuf.Collections.RepeatedField`1[[System.Single, mscorlib]], Assembly-CSharp",
    "$values": [
      0.0,
      0.0,
      0.0,
      0.0,
      0.0,
      0.0,
      0.0438466333,
      0.000459301344,
      29.07169,
      0.0007074957,
      0.0008243846,
      12.477272,
      25.0626373
    ]
  },
  {
    "$type": "Google.Protobuf.Collections.RepeatedField`1[[System.Single, mscorlib]], Assembly-CSharp",
    "$values": [
      0.0,
      0.0,
      0.0,
      0.0,
      0.0,
      0.0,
      11.81861,
      0.000670584,
      38.11405,
      0.0017095505,
      0.0020350737,
      12.47971,
      25.0668354
    ]
  },
  {
    "$type": "Google.Protobuf.Collections.RepeatedField`1[[System.Single, mscorlib]], Assembly-CSharp",
    "$values": [
      0.0,
      0.0,
      0.0,
      0.0,
      0.0,
      0.0,
      74.6368561,
      0.0008431917,
      12.77789,
      0.0011665998,
      0.033722423,
      4.161966,
      8.361988
    ]
  },
  {
    "$type": "Google.Protobuf.Collections.RepeatedField`1[[System.Single, mscorlib]], Assembly-CSharp",
    "$values": [
      0.0,
      0.0,
      0.0,
      0.0,
      0.0,
      0.0,
      95.71676,
      0.0005429093,
      0.06332769,
      0.0006625126,
      4.175378,
      0.00275920075,
      0.00964969
    ]
  },
  {
    "$type": "Google.Protobuf.Collections.RepeatedField`1[[System.Single, mscorlib]], Assembly-CSharp",
    "$values": [
      0.0,
      0.0,
      0.0,
      0.0,
      0.0,
      0.0,
      75.4444,
      0.0006910008,
      0.0592000671,
      0.0005786784,
      24.4508743,
      0.002596452,
      0.0113140475
    ]
  },
  {
    "$type": "Google.Protobuf.Collections.RepeatedField`1[[System.Single, mscorlib]], Assembly-CSharp",
    "$values": [
      0.0,
      0.0,
      0.0,
      0.0,
      0.0,
      0.0,
      54.6442223,
      0.0009762619,
      0.1096252,
      0.000494309061,
      45.20192,
      0.00217375741,
      0.0122402729
    ]
  },
  {
    "$type": "Google.Protobuf.Collections.RepeatedField`1[[System.Single, mscorlib]], Assembly-CSharp",
    "$values": [
      0.0,
      0.0,
      0.0,
      0.0,
      0.0,
      0.0,
      33.843956,
      0.00139316428,
      4.66117239,
      0.0006271099,
      61.4443321,
      0.0018978049,
      0.0139441276
    ]
  },
  {
    "$type": "Google.Protobuf.Collections.RepeatedField`1[[System.Single, mscorlib]], Assembly-CSharp",
    "$values": [
      0.0,
      0.0,
      0.0,
      0.0,
      0.0,
      0.0,
      13.042552,
      0.00139841461,
      25.16088,
      0.0007959873,
      61.7500763,
      0.001446098,
      0.0127055626
    ]
  },
  {
    "$type": "Google.Protobuf.Collections.RepeatedField`1[[System.Single, mscorlib]], Assembly-CSharp",
    "$values": [
      0.0,
      0.0,
      0.0,
      0.0,
      0.0,
      0.0,
      0.268528134,
      0.0009815678,
      78.96963,
      0.000789282261,
      20.6805134,
      0.0007261967,
      0.005408619
    ]
  },
  {
    "$type": "Google.Protobuf.Collections.RepeatedField`1[[System.Single, mscorlib]], Assembly-CSharp",
    "$values": [
      0.0,
      0.0,
      0.0,
      0.0,
      0.0,
      0.0,
      0.00486353133,
      0.000798236753,
      99.57481,
      0.000871997,
      0.317170173,
      0.000569761032,
      0.0026227904
    ]
  },
  {
    "$type": "Google.Protobuf.Collections.RepeatedField`1[[System.Single, mscorlib]], Assembly-CSharp",
    "$values": [
      0.0,
      0.0,
      0.0,
      0.0,
      0.0,
      0.0,
      0.00585720362,
      0.0008272223,
      99.2419739,
      0.00113279431,
      0.6449878,
      0.0006017325,
      0.002824314
    ]
  },
  {
    "$type": "Google.Protobuf.Collections.RepeatedField`1[[System.Single, mscorlib]], Assembly-CSharp",
    "$values": [
      0.0,
      0.0,
      0.0,
      0.0,
      0.0,
      0.0,
      0.0112452582,
      0.00124726386,
      84.15704,
      0.00139831472,
      15.6921616,
      0.000934020441,
      0.005212666
    ]
  },
  {
    "$type": "Google.Protobuf.Collections.RepeatedField`1[[System.Single, mscorlib]], Assembly-CSharp",
    "$values": [
      0.0,
      0.0,
      0.0,
      0.0,
      0.0,
      0.0,
      0.02068642,
      0.0017795841,
      63.4197235,
      0.00128878059,
      36.2646828,
      0.00136846607,
      0.007012651
    ]
  },
  {
    "$type": "Google.Protobuf.Collections.RepeatedField`1[[System.Single, mscorlib]], Assembly-CSharp",
    "$values": [
      0.0,
      0.0,
      0.0,
      0.0,
      0.0,
      0.0,
      0.03611527,
      0.002771186,
      42.67431,
      0.00118869182,
      56.3174248,
      0.001971782,
      0.01048097
    ]
  },
  {
    "$type": "Google.Protobuf.Collections.RepeatedField`1[[System.Single, mscorlib]], Assembly-CSharp",
    "$values": [
      0.0,
      0.0,
      0.0,
      0.0,
      0.0,
      0.0,
      0.08146187,
      0.0108945984,
      10.1146641,
      0.000609511335,
      53.3397331,
      0.00357252429,
      0.0292939059
    ]
  },
  {
    "$type": "Google.Protobuf.Collections.RepeatedField`1[[System.Single, mscorlib]], Assembly-CSharp",
    "$values": [
      0.0,
      0.0,
      0.0,
      0.0,
      0.0,
      0.0,
      0.0906999,
      0.0143404128,
      0.043073155,
      0.000359576778,
      40.6604919,
      0.00392760243,
      0.0346762463
    ]
  },
  {
    "$type": "Google.Protobuf.Collections.RepeatedField`1[[System.Single, mscorlib]], Assembly-CSharp",
    "$values": [
      0.0,
      0.0,
      0.0,
      0.0,
      0.0,
      0.0,
      0.07255151,
      0.012449991,
      0.0359947756,
      0.000330684,
      31.5637684,
      0.00324974558,
      0.0287455022
    ]
  },
  {
    "$type": "Google.Protobuf.Collections.RepeatedField`1[[System.Single, mscorlib]], Assembly-CSharp",
    "$values": [
      0.0,
      0.0,
      0.0,
      0.0,
      0.0,
      0.0,
      0.0517649539,
      0.009464677,
      0.0265604258,
      0.000257782725,
      21.901741,
      0.00238122838,
      0.0211181063
    ]
  },
  {
    "$type": "Google.Protobuf.Collections.RepeatedField`1[[System.Single, mscorlib]], Assembly-CSharp",
    "$values": [
      0.0,
      0.0,
      0.0,
      0.0,
      0.0,
      0.0,
      0.0309783947,
      0.00647936342,
      0.0171260722,
      0.000184881443,
      12.2397118,
      0.00151271117,
      0.0134907113
    ]
  },
  {
    "$type": "Google.Protobuf.Collections.RepeatedField`1[[System.Single, mscorlib]], Assembly-CSharp",
    "$values": [
      0.0,
      0.0,
      0.0,
      0.0,
      0.0,
      0.0,
      0.0101918392,
      0.00349404966,
      0.0076917205,
      0.000111980167,
      2.57768416,
      0.000644193846,
      0.00586331636
    ]
  },
  {
    "$type": "Google.Protobuf.Collections.RepeatedField`1[[System.Single, mscorlib]], Assembly-CSharp",
    "$values": [
      0.0,
      0.0,
      0.0,
      0.0,
      0.0,
      0.0,
      0.00131908094,
      0.000547446136,
      0.00117798685,
      2.2004253E-05,
      0.282653,
      9.53303243E-05,
      0.0008483259
    ]
  },
  {
    "$type": "Google.Protobuf.Collections.RepeatedField`1[[System.Single, mscorlib]], Assembly-CSharp",
    "$values": [
      0.0,
      0.0,
      0.0,
      0.0,
      0.0,
      0.0,
      0.0,
      0.0,
      0.0,
      0.0,
      0.0,
      0.0,
      0.0
    ]
  },
  {
    "$type": "Google.Protobuf.Collections.RepeatedField`1[[System.Single, mscorlib]], Assembly-CSharp",
    "$values": [
      0.0,
      0.0,
      0.0,
      0.0,
      0.0,
      0.0,
      0.0,
      0.0,
      0.0,
      0.0,
      0.0,
      0.0,
      0.0
    ]
  },
  {
    "$type": "Google.Protobuf.Collections.RepeatedField`1[[System.Single, mscorlib]], Assembly-CSharp",
    "$values": [
      0.0,
      0.0,
      0.0,
      0.0,
      0.0,
      0.0,
      0.0,
      0.0,
      0.0,
      0.0,
      0.0,
      0.0,
      0.0
    ]
  },
  {
    "$type": "Google.Protobuf.Collections.RepeatedField`1[[System.Single, mscorlib]], Assembly-CSharp",
    "$values": [
      0.0,
      0.0,
      0.0,
      0.0,
      0.0,
      0.0,
      0.0,
      0.0,
      0.0,
      0.0,
      0.0,
      0.0,
      0.0
    ]
  },
  {
    "$type": "Google.Protobuf.Collections.RepeatedField`1[[System.Single, mscorlib]], Assembly-CSharp",
    "$values": [
      0.0,
      0.0,
      0.0,
      0.0,
      0.0,
      0.0,
      0.0,
      0.0,
      0.0,
      0.0,
      0.0,
      0.0,
      0.0
    ]
  },
  {
    "$type": "Google.Protobuf.Collections.RepeatedField`1[[System.Single, mscorlib]], Assembly-CSharp",
    "$values": [
      0.0,
      0.0,
      0.0,
      0.0,
      0.0,
      0.0,
      0.0,
      0.0,
      0.0,
      0.0,
      0.0,
      0.0,
      0.0
    ]
  },
  {
    "$type": "Google.Protobuf.Collections.RepeatedField`1[[System.Single, mscorlib]], Assembly-CSharp",
    "$values": [
      0.0,
      0.0,
      0.0,
      0.0,
      0.0,
      0.0,
      0.0,
      0.0,
      0.0,
      0.0,
      0.0,
      0.0,
      0.0
    ]
  },
  {
    "$type": "Google.Protobuf.Collections.RepeatedField`1[[System.Single, mscorlib]], Assembly-CSharp",
    "$values": [
      0.0,
      0.0,
      0.0,
      0.0,
      0.0,
      0.0,
      0.0,
      0.0,
      0.0,
      0.0,
      0.0,
      0.0,
      0.0
    ]
  },
  {
    "$type": "Google.Protobuf.Collections.RepeatedField`1[[System.Single, mscorlib]], Assembly-CSharp",
    "$values": [
      0.0,
      0.0,
      0.0,
      0.0,
      0.0,
      0.0,
      0.0,
      0.0,
      0.0,
      0.0,
      0.0,
      0.0,
      0.0
    ]
  },
  {
    "$type": "Google.Protobuf.Collections.RepeatedField`1[[System.Single, mscorlib]], Assembly-CSharp",
    "$values": [
      0.0,
      0.0,
      0.0,
      0.0,
      0.0,
      0.0,
      0.0,
      0.0,
      0.0,
      0.0,
      0.0,
      0.0,
      0.0
    ]
  },
  {
    "$type": "Google.Protobuf.Collections.RepeatedField`1[[System.Single, mscorlib]], Assembly-CSharp",
    "$values": [
      0.0,
      0.0,
      0.0,
      0.0,
      0.0,
      0.0,
      0.0,
      0.0,
      0.0,
      0.0,
      0.0,
      0.0,
      0.0
    ]
  },
  {
    "$type": "Google.Protobuf.Collections.RepeatedField`1[[System.Single, mscorlib]], Assembly-CSharp",
    "$values": [
      0.0,
      0.0,
      0.0,
      0.0,
      0.0,
      0.0,
      0.0,
      0.0,
      0.0,
      0.0,
      0.0,
      0.0,
      0.0
    ]
  },
  {
    "$type": "Google.Protobuf.Collections.RepeatedField`1[[System.Single, mscorlib]], Assembly-CSharp",
    "$values": [
      0.0,
      0.0,
      0.0,
      0.0,
      0.0,
      0.0,
      0.0,
      0.0,
      0.0,
      0.0,
      0.0,
      0.0,
      0.0
    ]
  },
  {
    "$type": "Google.Protobuf.Collections.RepeatedField`1[[System.Single, mscorlib]], Assembly-CSharp",
    "$values": [
      0.0,
      0.0,
      0.0,
      0.0,
      0.0,
      0.0,
      0.0,
      0.0,
      0.0,
      0.0,
      0.0,
      0.0,
      0.0
    ]
  },
  {
    "$type": "Google.Protobuf.Collections.RepeatedField`1[[System.Single, mscorlib]], Assembly-CSharp",
    "$values": [
      0.0,
      0.0,
      0.0,
      0.0,
      0.0,
      0.0,
      0.0,
      0.0,
      0.0,
      0.0,
      0.0,
      0.0,
      0.0
    ]
  },
  {
    "$type": "Google.Protobuf.Collections.RepeatedField`1[[System.Single, mscorlib]], Assembly-CSharp",
    "$values": [
      0.0,
      0.0,
      0.0,
      0.0,
      0.0,
      0.0,
      0.0,
      0.0,
      0.0,
      0.0,
      0.0,
      0.0,
      0.0
    ]
  },
  {
    "$type": "Google.Protobuf.Collections.RepeatedField`1[[System.Single, mscorlib]], Assembly-CSharp",
    "$values": [
      0.0,
      0.0,
      0.0,
      0.0,
      0.0,
      0.0,
      0.0,
      0.0,
      0.0,
      0.0,
      0.0,
      0.0,
      0.0
    ]
  },
  {
    "$type": "Google.Protobuf.Collections.RepeatedField`1[[System.Single, mscorlib]], Assembly-CSharp",
    "$values": [
      0.0,
      0.0,
      0.0,
      0.0,
      0.0,
      0.0,
      0.00457319943,
      0.129256323,
      69.15229,
      0.00998987,
      1.13831544,
      0.0050534266,
      0.0133735342
    ]
  },
  {
    "$type": "Google.Protobuf.Collections.RepeatedField`1[[System.Single, mscorlib]], Assembly-CSharp",
    "$values": [
      0.0,
      0.0,
      0.0,
      0.0,
      0.0,
      0.0,
      5.72276E-05,
      0.00143166131,
      99.8949356,
      2.5254405E-05,
      0.09703434,
      0.0004802043,
      0.000106938263
    ]
  },
  {
    "$type": "Google.Protobuf.Collections.RepeatedField`1[[System.Single, mscorlib]], Assembly-CSharp",
    "$values": [
      0.0,
      0.0,
      0.0,
      0.0,
      0.0,
      0.0,
      5.39568355E-05,
      0.00146140193,
      99.88895,
      2.91586584E-05,
      0.103450686,
      0.0005349078,
      0.000153248344
    ]
  },
  {
    "$type": "Google.Protobuf.Collections.RepeatedField`1[[System.Single, mscorlib]], Assembly-CSharp",
    "$values": [
      0.0,
      0.0,
      0.0,
      0.0,
      0.0,
      0.0,
      7.499387E-05,
      0.00163272349,
      90.11473,
      4.68478E-05,
      9.876755,
      0.000694552262,
      0.00113660772
    ]
  },
  {
    "$type": "Google.Protobuf.Collections.RepeatedField`1[[System.Single, mscorlib]], Assembly-CSharp",
    "$values": [
      0.0,
      0.0,
      0.0,
      0.0,
      0.0,
      0.0,
      0.0004413072,
      0.00232200744,
      69.30868,
      0.000409805274,
      28.1140728,
      0.009697381,
      2.55924487
    ]
  },
  {
    "$type": "Google.Protobuf.Collections.RepeatedField`1[[System.Single, mscorlib]], Assembly-CSharp",
    "$values": [
      0.0,
      0.0,
      0.0,
      0.0,
      0.0,
      0.0,
      0.001265285,
      0.00454385951,
      48.5107574,
      0.00142145879,
      31.2956982,
      0.0310515277,
      20.148777
    ]
  },
  {
    "$type": "Google.Protobuf.Collections.RepeatedField`1[[System.Single, mscorlib]], Assembly-CSharp",
    "$values": [
      0.0,
      0.0,
      0.0,
      0.0,
      0.0,
      0.0,
      0.0007365144,
      0.004728773,
      12.0181971,
      0.000825793948,
      10.4357519,
      0.0120987631,
      77.52386
    ]
  },
  {
    "$type": "Google.Protobuf.Collections.RepeatedField`1[[System.Single, mscorlib]], Assembly-CSharp",
    "$values": [
      0.0,
      0.0,
      0.0,
      0.0,
      0.0,
      0.0,
      0.0005444168,
      0.00618007174,
      0.0170160551,
      0.000499043963,
      0.009779895,
      0.00150988065,
      99.96123
    ]
  },
  {
    "$type": "Google.Protobuf.Collections.RepeatedField`1[[System.Single, mscorlib]], Assembly-CSharp",
    "$values": [
      0.0,
      0.0,
      0.0,
      0.0,
      0.0,
      0.0,
      0.00101269537,
      0.0148023758,
      0.025016021,
      0.000792934967,
      0.010780802,
      0.00145864463,
      99.94062
    ]
  },
  {
    "$type": "Google.Protobuf.Collections.RepeatedField`1[[System.Single, mscorlib]], Assembly-CSharp",
    "$values": [
      0.0,
      0.0,
      0.0,
      0.0,
      0.0,
      0.0,
      0.0015365812,
      0.0301911421,
      0.03841539,
      0.00127139979,
      0.0132417725,
      0.00155238,
      99.9031
    ]
  },
  {
    "$type": "Google.Protobuf.Collections.RepeatedField`1[[System.Single, mscorlib]], Assembly-CSharp",
    "$values": [
      0.0,
      0.0,
      0.0,
      0.0,
      0.0,
      0.0,
      0.00188645022,
      0.040271502,
      0.04374213,
      0.00146642176,
      0.014068055,
      0.00152002892,
      99.87859
    ]
  },
  {
    "$type": "Google.Protobuf.Collections.RepeatedField`1[[System.Single, mscorlib]], Assembly-CSharp",
    "$values": [
      0.0,
      0.0,
      0.0,
      0.0,
      0.0,
      0.0,
      0.00218649488,
      0.047220435,
      0.0458903126,
      0.00157430337,
      0.0141017335,
      0.00143905682,
      99.84142
    ]
  },
  {
    "$type": "Google.Protobuf.Collections.RepeatedField`1[[System.Single, mscorlib]], Assembly-CSharp",
    "$values": [
      0.0,
      0.0,
      0.0,
      0.0,
      0.0,
      0.0,
      0.00346401939,
      0.0777954757,
      0.0450195447,
      0.000921830768,
      0.0187216122,
      0.0021949464,
      96.4636459
    ]
  },
  {
    "$type": "Google.Protobuf.Collections.RepeatedField`1[[System.Single, mscorlib]], Assembly-CSharp",
    "$values": [
      0.0,
      0.0,
      0.0,
      0.0,
      0.0,
      0.0,
      0.00450352067,
      0.120511174,
      0.05397001,
      0.000682444545,
      0.02451037,
      0.003153828,
      92.13305
    ]
  },
  {
    "$type": "Google.Protobuf.Collections.RepeatedField`1[[System.Single, mscorlib]], Assembly-CSharp",
    "$values": [
      0.0,
      0.0,
      0.0,
      0.0,
      0.0,
      0.0,
      0.00513633853,
      0.172446042,
      0.07088507,
      0.0009261545,
      0.031661734,
      0.00428548735,
      85.258934
    ]
  },
  {
    "$type": "Google.Protobuf.Collections.RepeatedField`1[[System.Single, mscorlib]], Assembly-CSharp",
    "$values": [
      0.0,
      0.0,
      0.0,
      0.0,
      0.0,
      0.0,
      0.005497646,
      0.24787882,
      0.09342259,
      0.00135493476,
      0.0402503721,
      0.005767797,
      71.10096
    ]
  },
  {
    "$type": "Google.Protobuf.Collections.RepeatedField`1[[System.Single, mscorlib]], Assembly-CSharp",
    "$values": [
      0.0,
      0.0,
      0.0,
      0.0,
      0.0,
      0.0,
      0.00529193366,
      0.306914359,
      0.113002144,
      0.00181715458,
      0.0463191159,
      0.00700118346,
      53.4507561
    ]
  },
  {
    "$type": "Google.Protobuf.Collections.RepeatedField`1[[System.Single, mscorlib]], Assembly-CSharp",
    "$values": [
      0.0,
      0.0,
      0.0,
      0.0,
      0.0,
      0.0,
      0.004449007,
      0.287909269,
      0.103796385,
      0.0017041195,
      0.0419068448,
      0.0064729536,
      33.69544
    ]
  },
  {
    "$type": "Google.Protobuf.Collections.RepeatedField`1[[System.Single, mscorlib]], Assembly-CSharp",
    "$values": [
      0.0,
      0.0,
      0.0,
      0.0,
      0.0,
      0.0,
      0.00121152564,
      0.08570689,
      0.0305956434,
      0.000513710547,
      0.0123988222,
      0.0019139183,
      7.83118868
    ]
  },
  {
    "$type": "Google.Protobuf.Collections.RepeatedField`1[[System.Single, mscorlib]], Assembly-CSharp",
    "$values": [
      0.0,
      0.0,
      0.0,
      0.0,
      0.0,
      0.0,
      0.0,
      0.0,
      0.0,
      0.0,
      0.0,
      0.0,
      0.0
    ]
  },
  {
    "$type": "Google.Protobuf.Collections.RepeatedField`1[[System.Single, mscorlib]], Assembly-CSharp",
    "$values": [
      0.0,
      0.0,
      0.0,
      0.0,
      0.0,
      0.0,
      0.0,
      0.0,
      0.0,
      0.0,
      0.0,
      0.0,
      0.0
    ]
  },
  {
    "$type": "Google.Protobuf.Collections.RepeatedField`1[[System.Single, mscorlib]], Assembly-CSharp",
    "$values": [
      0.0,
      0.0,
      0.0,
      0.0,
      0.0,
      0.0,
      0.0,
      0.0,
      0.0,
      0.0,
      0.0,
      0.0,
      0.0
    ]
  },
  {
    "$type": "Google.Protobuf.Collections.RepeatedField`1[[System.Single, mscorlib]], Assembly-CSharp",
    "$values": [
      0.0,
      0.0,
      0.0,
      0.0,
      0.0,
      0.0,
      0.0,
      0.0,
      0.0,
      0.0,
      0.0,
      0.0,
      0.0
    ]
  },
  {
    "$type": "Google.Protobuf.Collections.RepeatedField`1[[System.Single, mscorlib]], Assembly-CSharp",
    "$values": [
      0.0,
      0.0,
      0.0,
      0.0,
      0.0,
      0.0,
      0.0,
      0.0,
      0.0,
      0.0,
      0.0,
      0.0,
      0.0
    ]
  },
  {
    "$type": "Google.Protobuf.Collections.RepeatedField`1[[System.Single, mscorlib]], Assembly-CSharp",
    "$values": [
      0.0,
      0.0,
      0.0,
      0.0,
      0.0,
      0.0,
      0.0,
      0.0,
      0.0,
      0.0,
      0.0,
      0.0,
      0.0
    ]
  },
  {
    "$type": "Google.Protobuf.Collections.RepeatedField`1[[System.Single, mscorlib]], Assembly-CSharp",
    "$values": [
      0.0,
      0.0,
      0.0,
      0.0,
      0.0,
      0.0,
      0.0,
      0.0,
      0.0,
      0.0,
      0.0,
      0.0,
      0.0
    ]
  },
  {
    "$type": "Google.Protobuf.Collections.RepeatedField`1[[System.Single, mscorlib]], Assembly-CSharp",
    "$values": [
      0.0,
      0.0,
      0.0,
      0.0,
      0.0,
      0.0,
      0.0,
      0.0,
      0.0,
      0.0,
      0.0,
      0.0,
      0.0
    ]
  },
  {
    "$type": "Google.Protobuf.Collections.RepeatedField`1[[System.Single, mscorlib]], Assembly-CSharp",
    "$values": [
      0.0,
      0.0,
      0.0,
      0.0,
      0.0,
      0.0,
      0.0,
      0.0,
      0.0,
      0.0,
      0.0,
      0.0,
      0.0
    ]
  },
  {
    "$type": "Google.Protobuf.Collections.RepeatedField`1[[System.Single, mscorlib]], Assembly-CSharp",
    "$values": [
      0.0,
      0.0,
      0.0,
      0.0,
      0.0,
      0.0,
      0.0,
      0.0,
      0.0,
      0.0,
      0.0,
      0.0,
      0.0
    ]
  },
  {
    "$type": "Google.Protobuf.Collections.RepeatedField`1[[System.Single, mscorlib]], Assembly-CSharp",
    "$values": [
      0.0,
      0.0,
      0.0,
      0.0,
      0.0,
      0.0,
      0.0,
      0.0,
      0.0,
      0.0,
      0.0,
      0.0,
      0.0
    ]
  },
  {
    "$type": "Google.Protobuf.Collections.RepeatedField`1[[System.Single, mscorlib]], Assembly-CSharp",
    "$values": [
      0.0,
      0.0,
      0.0,
      0.0,
      0.0,
      0.0,
      0.0,
      0.0,
      0.0,
      0.0,
      0.0,
      0.0,
      0.0
    ]
  },
  {
    "$type": "Google.Protobuf.Collections.RepeatedField`1[[System.Single, mscorlib]], Assembly-CSharp",
    "$values": [
      0.0,
      0.0,
      0.0,
      0.0,
      0.0,
      0.0,
      0.0,
      0.0,
      0.0,
      0.0,
      0.0,
      0.0,
      0.0
    ]
  },
  {
    "$type": "Google.Protobuf.Collections.RepeatedField`1[[System.Single, mscorlib]], Assembly-CSharp",
    "$values": [
      0.0,
      0.0,
      0.0,
      0.0,
      0.0,
      0.0,
      0.0,
      0.0,
      0.0,
      0.0,
      0.0,
      0.0,
      0.0
    ]
  },
  {
    "$type": "Google.Protobuf.Collections.RepeatedField`1[[System.Single, mscorlib]], Assembly-CSharp",
    "$values": [
      0.0,
      0.0,
      0.0,
      0.0,
      0.0,
      0.0,
      0.0,
      0.0,
      0.0,
      0.0,
      0.0,
      0.0,
      0.0
    ]
  },
  {
    "$type": "Google.Protobuf.Collections.RepeatedField`1[[System.Single, mscorlib]], Assembly-CSharp",
    "$values": [
      0.0,
      0.0,
      0.0,
      0.0,
      0.0,
      0.0,
      0.0,
      0.0,
      0.0,
      0.0,
      0.0,
      0.0,
      0.0
    ]
  },
  {
    "$type": "Google.Protobuf.Collections.RepeatedField`1[[System.Single, mscorlib]], Assembly-CSharp",
    "$values": [
      0.0,
      0.0,
      0.0,
      0.0,
      0.0,
      0.0,
      0.0,
      0.0,
      0.0,
      0.0,
      0.0,
      0.0,
      0.0
    ]
  },
  {
    "$type": "Google.Protobuf.Collections.RepeatedField`1[[System.Single, mscorlib]], Assembly-CSharp",
    "$values": [
      0.0,
      0.0,
      0.0,
      0.0,
      0.0,
      0.0,
      0.0,
      0.0,
      0.0,
      0.0,
      0.0,
      0.0,
      0.0
    ]
  },
  {
    "$type": "Google.Protobuf.Collections.RepeatedField`1[[System.Single, mscorlib]], Assembly-CSharp",
    "$values": [
      0.0,
      0.0,
      0.0,
      0.0,
      0.0,
      0.0,
      0.00299421861,
      7.651171E-05,
      4.161698,
      0.000152714754,
      6.63907049E-05,
      0.000103358667,
      6.681138E-05
    ]
  },
  {
    "$type": "Google.Protobuf.Collections.RepeatedField`1[[System.Single, mscorlib]], Assembly-CSharp",
    "$values": [
      0.0,
      0.0,
      0.0,
      0.0,
      0.0,
      0.0,
      0.0179278813,
      0.00050924794,
      24.9717464,
      0.000844358234,
      0.0003686432,
      0.000618845166,
      0.000394878851
    ]
  },
  {
    "$type": "Google.Protobuf.Collections.RepeatedField`1[[System.Single, mscorlib]], Assembly-CSharp",
    "$values": [
      0.0,
      0.0,
      0.0,
      0.0,
      0.0,
      0.0,
      8.230792,
      0.0009539296,
      37.57872,
      0.00148138124,
      0.003098249,
      0.00119610329,
      0.006362979
    ]
  },
  {
    "$type": "Google.Protobuf.Collections.RepeatedField`1[[System.Single, mscorlib]], Assembly-CSharp",
    "$values": [
      0.0,
      0.0,
      0.0,
      0.0,
      0.0,
      0.0,
      25.093977,
      0.00135228678,
      41.50961,
      0.00162156241,
      0.0255947225,
      0.00153741078,
      0.0177004468
    ]
  },
  {
    "$type": "Google.Protobuf.Collections.RepeatedField`1[[System.Single, mscorlib]], Assembly-CSharp",
    "$values": [
      0.0,
      0.0,
      0.0,
      0.0,
      0.0,
      0.0,
      25.75007,
      0.001661109,
      61.65057,
      0.0017339685,
      0.05713813,
      0.00161794713,
      0.0192941912
    ]
  },
  {
    "$type": "Google.Protobuf.Collections.RepeatedField`1[[System.Single, mscorlib]], Assembly-CSharp",
    "$values": [
      0.0,
      0.0,
      0.0,
      0.0,
      0.0,
      0.0,
      8.583477,
      0.000951696071,
      91.29988,
      0.0008930531,
      0.09698491,
      0.000830249046,
      0.00659452053
    ]
  },
  {
    "$type": "Google.Protobuf.Collections.RepeatedField`1[[System.Single, mscorlib]], Assembly-CSharp",
    "$values": [
      0.0,
      0.0,
      0.0,
      0.0,
      0.0,
      0.0,
      0.000850550132,
      0.0012619287,
      93.05006,
      0.000741833239,
      6.938905,
      0.0005115178,
      0.0005039896
    ]
  },
  {
    "$type": "Google.Protobuf.Collections.RepeatedField`1[[System.Single, mscorlib]], Assembly-CSharp",
    "$values": [
      0.0,
      0.0,
      0.0,
      0.0,
      0.0,
      0.0,
      0.00300740451,
      0.00155910244,
      72.2454453,
      0.0006720348,
      27.73974,
      0.00060243177,
      0.000749339466
    ]
  },
  {
    "$type": "Google.Protobuf.Collections.RepeatedField`1[[System.Single, mscorlib]], Assembly-CSharp",
    "$values": [
      0.0,
      0.0,
      0.0,
      0.0,
      0.0,
      0.0,
      0.00661574025,
      0.005090761,
      51.8760262,
      0.000675396,
      48.0939,
      0.002143395,
      0.00223913114
    ]
  },
  {
    "$type": "Google.Protobuf.Collections.RepeatedField`1[[System.Single, mscorlib]], Assembly-CSharp",
    "$values": [
      0.0,
      0.0,
      0.0,
      0.0,
      0.0,
      0.0,
      0.00735848444,
      0.0064369454,
      33.1871758,
      0.000648041954,
      66.7769852,
      0.00331176631,
      0.00280241016
    ]
  },
  {
    "$type": "Google.Protobuf.Collections.RepeatedField`1[[System.Single, mscorlib]], Assembly-CSharp",
    "$values": [
      0.0,
      0.0,
      0.0,
      0.0,
      0.0,
      0.0,
      0.007383336,
      0.00654759863,
      14.0295277,
      0.0005888986,
      85.932106,
      0.0037611085,
      0.00283785746
    ]
  },
  {
    "$type": "Google.Protobuf.Collections.RepeatedField`1[[System.Single, mscorlib]], Assembly-CSharp",
    "$values": [
      0.0,
      0.0,
      0.0,
      0.0,
      0.0,
      0.0,
      0.00419852743,
      0.00278709386,
      2.02113271,
      0.000450473337,
      97.91929,
      0.003751462,
      0.0322502144
    ]
  },
  {
    "$type": "Google.Protobuf.Collections.RepeatedField`1[[System.Single, mscorlib]], Assembly-CSharp",
    "$values": [
      0.0,
      0.0,
      0.0,
      0.0,
      0.0,
      0.0,
      0.00261532841,
      0.00103889371,
      0.4028495,
      0.00046956772,
      99.52771,
      0.00308582652,
      0.0493795238
    ]
  },
  {
    "$type": "Google.Protobuf.Collections.RepeatedField`1[[System.Single, mscorlib]], Assembly-CSharp",
    "$values": [
      0.0,
      0.0,
      0.0,
      0.0,
      0.0,
      0.0,
      0.002375843,
      0.0008698147,
      12.9398136,
      0.000375017145,
      86.9877243,
      0.00256954134,
      0.055256173
    ]
  },
  {
    "$type": "Google.Protobuf.Collections.RepeatedField`1[[System.Single, mscorlib]], Assembly-CSharp",
    "$values": [
      0.0,
      0.0,
      0.0,
      0.0,
      0.0,
      0.0,
      0.001828642,
      0.0007003144,
      33.67533,
      0.000273815123,
      66.26062,
      0.002123768,
      0.0482182
    ]
  },
  {
    "$type": "Google.Protobuf.Collections.RepeatedField`1[[System.Single, mscorlib]], Assembly-CSharp",
    "$values": [
      0.0,
      0.0,
      0.0,
      0.0,
      0.0,
      0.0,
      0.00132585259,
      0.00103054789,
      50.4885368,
      0.000211156483,
      45.5432854,
      0.001673113,
      3.9512527
    ]
  },
  {
    "$type": "Google.Protobuf.Collections.RepeatedField`1[[System.Single, mscorlib]], Assembly-CSharp",
    "$values": [
      0.0,
      0.0,
      0.0,
      0.0,
      0.0,
      0.0,
      0.00103881164,
      0.00277676946,
      50.94333,
      0.00015696467,
      24.8317738,
      0.00115794665,
      24.2067719
    ]
  },
  {
    "$type": "Google.Protobuf.Collections.RepeatedField`1[[System.Single, mscorlib]], Assembly-CSharp",
    "$values": [
      0.0,
      0.0,
      0.0,
      0.0,
      0.0,
      0.0,
      0.00231879437,
      0.0411811247,
      82.8992157,
      0.0002749019,
      5.00632572,
      0.0133391833,
      12.0259228
    ]
  },
  {
    "$type": "Google.Protobuf.Collections.RepeatedField`1[[System.Single, mscorlib]], Assembly-CSharp",
    "$values": [
      0.0,
      0.0,
      0.0,
      0.0,
      0.0,
      0.0,
      0.006767624,
      0.04302522,
      86.89597,
      0.000351893861,
      12.9993877,
      0.0192893222,
      0.0229363963
    ]
  },
  {
    "$type": "Google.Protobuf.Collections.RepeatedField`1[[System.Single, mscorlib]], Assembly-CSharp",
    "$values": [
      0.0,
      0.0,
      0.0,
      0.0,
      0.0,
      0.0,
      0.0100011565,
      0.03317045,
      66.37333,
      0.000388788321,
      33.5365448,
      0.015696004,
      0.0194774084
    ]
  },
  {
    "$type": "Google.Protobuf.Collections.RepeatedField`1[[System.Single, mscorlib]], Assembly-CSharp",
    "$values": [
      0.0,
      0.0,
      0.0,
      0.0,
      0.0,
      0.0,
      0.023545377,
      0.0245199148,
      45.8801079,
      0.0004797156,
      54.02351,
      0.0124446694,
      0.0216003917
    ]
  },
  {
    "$type": "Google.Protobuf.Collections.RepeatedField`1[[System.Single, mscorlib]], Assembly-CSharp",
    "$values": [
      0.0,
      0.0,
      0.0,
      0.0,
      0.0,
      0.0,
      0.0282117873,
      0.0153700942,
      25.3857517,
      0.000478279282,
      74.52812,
      0.008848859,
      0.0194887277
    ]
  },
  {
    "$type": "Google.Protobuf.Collections.RepeatedField`1[[System.Single, mscorlib]], Assembly-CSharp",
    "$values": [
      0.0,
      0.0,
      0.0,
      0.0,
      0.0,
      0.0,
      0.0277278032,
      0.00563277,
      4.887283,
      0.000432067231,
      95.04694,
      0.005083077,
      0.01463503
    ]
  },
  {
    "$type": "Google.Protobuf.Collections.RepeatedField`1[[System.Single, mscorlib]], Assembly-CSharp",
    "$values": [
      0.0,
      0.0,
      0.0,
      0.0,
      0.0,
      0.0,
      0.008717816,
      0.0028918758,
      0.133245185,
      0.00151754241,
      99.81813,
      0.00096037914,
      0.0283200275
    ]
  },
  {
    "$type": "Google.Protobuf.Collections.RepeatedField`1[[System.Single, mscorlib]], Assembly-CSharp",
    "$values": [
      0.0,
      0.0,
      0.0,
      0.0,
      0.0,
      0.0,
      0.00133609469,
      0.00272133737,
      4.330237,
      0.00276779733,
      95.62436,
      0.000675603631,
      0.033624243
    ]
  },
  {
    "$type": "Google.Protobuf.Collections.RepeatedField`1[[System.Single, mscorlib]], Assembly-CSharp",
    "$values": [
      0.0,
      0.0,
      0.0,
      0.0,
      0.0,
      0.0,
      0.00121813721,
      0.002348777,
      25.1038952,
      0.003389065,
      74.85878,
      0.000563134265,
      0.0262829736
    ]
  },
  {
    "$type": "Google.Protobuf.Collections.RepeatedField`1[[System.Single, mscorlib]], Assembly-CSharp",
    "$values": [
      0.0,
      0.0,
      0.0,
      0.0,
      0.0,
      0.0,
      0.00102956616,
      0.001941277,
      45.90999,
      0.00421856763,
      54.0602722,
      0.000456725218,
      0.0187694971
    ]
  },
  {
    "$type": "Google.Protobuf.Collections.RepeatedField`1[[System.Single, mscorlib]], Assembly-CSharp",
    "$values": [
      0.0,
      0.0,
      0.0,
      0.0,
      0.0,
      0.0,
      0.0009178592,
      0.00145356508,
      66.7162247,
      0.004823178,
      33.262,
      0.0004055492,
      0.011264177
    ]
  },
  {
    "$type": "Google.Protobuf.Collections.RepeatedField`1[[System.Single, mscorlib]], Assembly-CSharp",
    "$values": [
      0.0,
      0.0,
      0.0,
      0.0,
      0.0,
      0.0,
      0.01594417,
      0.00239440915,
      87.49663,
      0.00726728933,
      12.4658375,
      0.00386624085,
      0.00482621044
    ]
  },
  {
    "$type": "Google.Protobuf.Collections.RepeatedField`1[[System.Single, mscorlib]], Assembly-CSharp",
    "$values": [
      0.0,
      0.0,
      0.0,
      0.0,
      0.0,
      0.0,
      0.02731592,
      0.0151320491,
      99.8994751,
      0.00359514076,
      0.0298209041,
      0.008929089,
      0.004155545
    ]
  },
  {
    "$type": "Google.Protobuf.Collections.RepeatedField`1[[System.Single, mscorlib]], Assembly-CSharp",
    "$values": [
      0.0,
      0.0,
      0.0,
      0.0,
      0.0,
      0.0,
      0.0245796684,
      0.018591892,
      99.9134,
      0.001695348,
      0.0144206528,
      0.00924369,
      0.004377719
    ]
  },
  {
    "$type": "Google.Protobuf.Collections.RepeatedField`1[[System.Single, mscorlib]], Assembly-CSharp",
    "$values": [
      0.0,
      0.0,
      0.0,
      0.0,
      0.0,
      0.0,
      0.33136788,
      0.0155696552,
      99.60991,
      0.00148334354,
      0.0139233274,
      0.008228156,
      0.006328049
    ]
  },
  {
    "$type": "Google.Protobuf.Collections.RepeatedField`1[[System.Single, mscorlib]], Assembly-CSharp",
    "$values": [
      0.0,
      0.0,
      0.0,
      0.0,
      0.0,
      0.0,
      15.6382961,
      0.011835251,
      84.26783,
      0.005855357,
      0.026609648,
      0.008045431,
      0.0253655277
    ]
  },
  {
    "$type": "Google.Protobuf.Collections.RepeatedField`1[[System.Single, mscorlib]], Assembly-CSharp",
    "$values": [
      0.0,
      0.0,
      0.0,
      0.0,
      0.0,
      0.0,
      17.1205235,
      0.007627248,
      82.7804947,
      0.0101527441,
      0.0274048,
      0.006717138,
      0.031751968
    ]
  },
  {
    "$type": "Google.Protobuf.Collections.RepeatedField`1[[System.Single, mscorlib]], Assembly-CSharp",
    "$values": [
      0.0,
      0.0,
      0.0,
      0.0,
      0.0,
      0.0,
      17.1157417,
      0.003232389,
      82.79355,
      0.0119187953,
      0.02427334,
      0.00485436,
      0.0320827365
    ]
  },
  {
    "$type": "Google.Protobuf.Collections.RepeatedField`1[[System.Single, mscorlib]], Assembly-CSharp",
    "$values": [
      0.0,
      0.0,
      0.0,
      0.0,
      0.0,
      0.0,
      5.70557928,
      0.00112020713,
      94.20783,
      0.00662879925,
      0.008442931,
      0.0028938672,
      0.05225544
    ]
  },
  {
    "$type": "Google.Protobuf.Collections.RepeatedField`1[[System.Single, mscorlib]], Assembly-CSharp",
    "$values": [
      0.0,
      0.0,
      0.0,
      0.0,
      0.0,
      0.0,
      0.000706584833,
      0.0006119221,
      97.6786957,
      0.004179935,
      0.000861988345,
      0.00400096457,
      2.29578376
    ]
  },
  {
    "$type": "Google.Protobuf.Collections.RepeatedField`1[[System.Single, mscorlib]], Assembly-CSharp",
    "$values": [
      0.0,
      0.0,
      0.0,
      0.0,
      0.0,
      0.0,
      0.00156597537,
      0.000915950746,
      80.7916,
      0.00451563345,
      0.00182075636,
      0.0105173811,
      19.174118
    ]
  },
  {
    "$type": "Google.Protobuf.Collections.RepeatedField`1[[System.Single, mscorlib]], Assembly-CSharp",
    "$values": [
      0.0,
      0.0,
      0.0,
      0.0,
      0.0,
      0.0,
      0.00255537452,
      0.008121451,
      71.19325,
      0.003885219,
      0.00342511642,
      0.0167812835,
      28.75884
    ]
  },
  {
    "$type": "Google.Protobuf.Collections.RepeatedField`1[[System.Single, mscorlib]], Assembly-CSharp",
    "$values": [
      0.0,
      0.0,
      0.0,
      0.0,
      0.0,
      0.0,
      0.00362485438,
      0.0157700758,
      68.95292,
      0.00320313452,
      2.241067,
      0.0177064668,
      28.7545147
    ]
  },
  {
    "$type": "Google.Protobuf.Collections.RepeatedField`1[[System.Single, mscorlib]], Assembly-CSharp",
    "$values": [
      0.0,
      0.0,
      0.0,
      0.0,
      0.0,
      0.0,
      0.00676650275,
      0.0192640647,
      51.9982758,
      0.00253246049,
      19.1980038,
      0.018213829,
      28.7471981
    ]
  },
  {
    "$type": "Google.Protobuf.Collections.RepeatedField`1[[System.Single, mscorlib]], Assembly-CSharp",
    "$values": [
      0.0,
      0.0,
      0.0,
      0.0,
      0.0,
      0.0,
      0.006794739,
      0.008491264,
      13.5362492,
      0.000638422149,
      76.84573,
      0.007731807,
      9.583813
    ]
  },
  {
    "$type": "Google.Protobuf.Collections.RepeatedField`1[[System.Single, mscorlib]], Assembly-CSharp",
    "$values": [
      0.0,
      0.0,
      0.0,
      0.0,
      0.0,
      0.0,
      0.005323655,
      0.00226699677,
      17.0730476,
      4.14083843E-05,
      82.87921,
      0.0107987663,
      0.0181570146
    ]
  },
  {
    "$type": "Google.Protobuf.Collections.RepeatedField`1[[System.Single, mscorlib]], Assembly-CSharp",
    "$values": [
      0.0,
      0.0,
      0.0,
      0.0,
      0.0,
      0.0,
      0.00413408456,
      0.00253933575,
      37.7348328,
      4.76059322E-05,
      62.2060738,
      0.0257955361,
      0.0139449146
    ]
  },
  {
    "$type": "Google.Protobuf.Collections.RepeatedField`1[[System.Single, mscorlib]], Assembly-CSharp",
    "$values": [
      0.0,
      0.0,
      0.0,
      0.0,
      0.0,
      0.0,
      0.008190446,
      0.002485779,
      37.9295425,
      0.000107497639,
      62.0038376,
      0.03059143,
      0.0105783558
    ]
  },
  {
    "$type": "Google.Protobuf.Collections.RepeatedField`1[[System.Single, mscorlib]], Assembly-CSharp",
    "$values": [
      0.0,
      0.0,
      0.0,
      0.0,
      0.0,
      0.0,
      0.0131439613,
      0.00226868526,
      37.8401,
      0.000214613436,
      62.0872955,
      0.0306461882,
      0.007906158
    ]
  },
  {
    "$type": "Google.Protobuf.Collections.RepeatedField`1[[System.Single, mscorlib]], Assembly-CSharp",
    "$values": [
      0.0,
      0.0,
      0.0,
      0.0,
      0.0,
      0.0,
      0.0201462731,
      0.00307536777,
      37.7941246,
      0.000279217958,
      62.1133957,
      0.0309571531,
      0.01121333
    ]
  },
  {
    "$type": "Google.Protobuf.Collections.RepeatedField`1[[System.Single, mscorlib]], Assembly-CSharp",
    "$values": [
      0.0,
      0.0,
      0.0,
      0.0,
      0.0,
      0.0,
      0.0107624652,
      0.00642591342,
      8.463318,
      0.00014695061,
      91.4042053,
      0.009052029,
      0.0847459957
    ]
  },
  {
    "$type": "Google.Protobuf.Collections.RepeatedField`1[[System.Single, mscorlib]], Assembly-CSharp",
    "$values": [
      0.0,
      0.0,
      0.0,
      0.0,
      0.0,
      0.0,
      0.00181000656,
      0.006799903,
      0.107795283,
      5.13838168E-05,
      99.74821,
      0.000329752,
      0.123809412
    ]
  },
  {
    "$type": "Google.Protobuf.Collections.RepeatedField`1[[System.Single, mscorlib]], Assembly-CSharp",
    "$values": [
      0.0,
      0.0,
      0.0,
      0.0,
      0.0,
      0.0,
      0.002058372,
      0.00587503659,
      12.35512,
      0.000189853323,
      87.50329,
      0.000455292582,
      0.120494865
    ]
  },
  {
    "$type": "Google.Protobuf.Collections.RepeatedField`1[[System.Single, mscorlib]], Assembly-CSharp",
    "$values": [
      0.0,
      0.0,
      0.0,
      0.0,
      0.0,
      0.0,
      0.00173759239,
      0.00439549563,
      33.17005,
      0.000230671023,
      66.71533,
      0.000441509736,
      0.09630417
    ]
  },
  {
    "$type": "Google.Protobuf.Collections.RepeatedField`1[[System.Single, mscorlib]], Assembly-CSharp",
    "$values": [
      0.0,
      0.0,
      0.0,
      0.0,
      0.0,
      0.0,
      0.00141806831,
      0.00292739947,
      53.9892464,
      0.000305273,
      45.9212532,
      0.000475792825,
      0.0720925555
    ]
  },
  {
    "$type": "Google.Protobuf.Collections.RepeatedField`1[[System.Single, mscorlib]], Assembly-CSharp",
    "$values": [
      0.0,
      0.0,
      0.0,
      0.0,
      0.0,
      0.0,
      0.00109211507,
      0.0014632087,
      74.80274,
      0.000452230626,
      25.1338367,
      0.000524637231,
      0.0479449555
    ]
  },
  {
    "$type": "Google.Protobuf.Collections.RepeatedField`1[[System.Single, mscorlib]], Assembly-CSharp",
    "$values": [
      0.0,
      0.0,
      0.0,
      0.0,
      0.0,
      0.0,
      0.006119849,
      0.00197217846,
      26.2999744,
      0.00144701428,
      73.6357346,
      0.00144931627,
      0.04347549
    ]
  },
  {
    "$type": "Google.Protobuf.Collections.RepeatedField`1[[System.Single, mscorlib]], Assembly-CSharp",
    "$values": [
      0.0,
      0.0,
      0.0,
      0.0,
      0.0,
      0.0,
      0.0100840116,
      0.00258238148,
      4.003297,
      0.0003963211,
      95.92283,
      0.003666022,
      0.0483172461
    ]
  },
  {
    "$type": "Google.Protobuf.Collections.RepeatedField`1[[System.Single, mscorlib]], Assembly-CSharp",
    "$values": [
      0.0,
      0.0,
      0.0,
      0.0,
      0.0,
      0.0,
      0.009604751,
      0.00273443363,
      23.1299419,
      0.000460094452,
      76.79388,
      0.00707520125,
      0.0450322069
    ]
  },
  {
    "$type": "Google.Protobuf.Collections.RepeatedField`1[[System.Single, mscorlib]], Assembly-CSharp",
    "$values": [
      0.0,
      0.0,
      0.0,
      0.0,
      0.0,
      0.0,
      0.007950347,
      0.002478902,
      43.9358864,
      0.0004561826,
      55.98516,
      0.008725284,
      0.0462630354
    ]
  },
  {
    "$type": "Google.Protobuf.Collections.RepeatedField`1[[System.Single, mscorlib]], Assembly-CSharp",
    "$values": [
      0.0,
      0.0,
      0.0,
      0.0,
      0.0,
      0.0,
      0.006893476,
      0.00268140924,
      60.2042274,
      0.0005331259,
      35.17604,
      0.0118489284,
      4.580896
    ]
  },
  {
    "$type": "Google.Protobuf.Collections.RepeatedField`1[[System.Single, mscorlib]], Assembly-CSharp",
    "$values": [
      0.0,
      0.0,
      0.0,
      0.0,
      0.0,
      0.0,
      0.00697100768,
      0.00364277046,
      60.22106,
      0.0009295806,
      14.3660631,
      0.0133807007,
      25.3700161
    ]
  },
  {
    "$type": "Google.Protobuf.Collections.RepeatedField`1[[System.Single, mscorlib]], Assembly-CSharp",
    "$values": [
      0.0,
      0.0,
      0.0,
      0.0,
      0.0,
      0.0,
      0.005316231,
      64.27133,
      19.8947487,
      0.0129265683,
      0.8409196,
      0.145803,
      14.8127432
    ]
  },
  {
    "$type": "Google.Protobuf.Collections.RepeatedField`1[[System.Single, mscorlib]], Assembly-CSharp",
    "$values": [
      0.0,
      0.0,
      0.0,
      0.0,
      0.0,
      0.0,
      0.004076801,
      96.93366,
      0.0228558481,
      0.0123035386,
      0.00135850906,
      0.212177426,
      2.8002634
    ]
  },
  {
    "$type": "Google.Protobuf.Collections.RepeatedField`1[[System.Single, mscorlib]], Assembly-CSharp",
    "$values": [
      0.0,
      0.0,
      0.0,
      0.0,
      0.0,
      0.0,
      0.009606537,
      97.59039,
      0.02679453,
      0.0113740927,
      0.00132793188,
      0.237216935,
      2.11116624
    ]
  },
  {
    "$type": "Google.Protobuf.Collections.RepeatedField`1[[System.Single, mscorlib]], Assembly-CSharp",
    "$values": [
      0.0,
      0.0,
      0.0,
      0.0,
      0.0,
      0.0,
      8.534925,
      89.5942154,
      0.186621219,
      0.009944946,
      0.00381840975,
      0.235037476,
      1.42073894
    ]
  },
  {
    "$type": "Google.Protobuf.Collections.RepeatedField`1[[System.Single, mscorlib]], Assembly-CSharp",
    "$values": [
      0.0,
      0.0,
      0.0,
      0.0,
      0.0,
      0.0,
      29.2019615,
      69.5703049,
      0.270723164,
      0.00748343673,
      0.006429874,
      0.1947657,
      0.727575362
    ]
  },
  {
    "$type": "Google.Protobuf.Collections.RepeatedField`1[[System.Single, mscorlib]], Assembly-CSharp",
    "$values": [
      0.0,
      0.0,
      0.0,
      0.0,
      0.0,
      0.0,
      49.91142,
      49.4888954,
      0.3502647,
      0.005031516,
      0.0114225037,
      0.153721735,
      0.0362118632
    ]
  },
  {
    "$type": "Google.Protobuf.Collections.RepeatedField`1[[System.Single, mscorlib]], Assembly-CSharp",
    "$values": [
      0.0,
      0.0,
      0.0,
      0.0,
      0.0,
      0.0,
      86.94827,
      12.3517866,
      0.300914079,
      0.002393794,
      0.0319369361,
      0.0489483178,
      0.02616159
    ]
  },
  {
    "$type": "Google.Protobuf.Collections.RepeatedField`1[[System.Single, mscorlib]], Assembly-CSharp",
    "$values": [
      0.0,
      0.0,
      0.0,
      0.0,
      0.0,
      0.0,
      99.18802,
      0.00656089559,
      0.2342634,
      0.0009911894,
      0.0326034,
      0.00874501,
      0.0245825127
    ]
  },
  {
    "$type": "Google.Protobuf.Collections.RepeatedField`1[[System.Single, mscorlib]], Assembly-CSharp",
    "$values": [
      0.0,
      0.0,
      0.0,
      0.0,
      0.0,
      0.0,
      97.05723,
      0.007240993,
      0.285397232,
      0.00108338543,
      0.0375351459,
      0.00883096,
      0.0256330818
    ]
  },
  {
    "$type": "Google.Protobuf.Collections.RepeatedField`1[[System.Single, mscorlib]], Assembly-CSharp",
    "$values": [
      0.0,
      0.0,
      0.0,
      0.0,
      0.0,
      0.0,
      82.63883,
      0.00748074055,
      0.3158628,
      0.00112656271,
      0.0402852,
      0.008072324,
      0.0236177668
    ]
  },
  {
    "$type": "Google.Protobuf.Collections.RepeatedField`1[[System.Single, mscorlib]], Assembly-CSharp",
    "$values": [
      0.0,
      0.0,
      0.0,
      0.0,
      0.0,
      0.0,
      61.94202,
      0.006133197,
      0.267187357,
      0.000916397,
      0.03349756,
      0.00622840133,
      0.0185642783
    ]
  },
  {
    "$type": "Google.Protobuf.Collections.RepeatedField`1[[System.Single, mscorlib]], Assembly-CSharp",
    "$values": [
      0.0,
      0.0,
      0.0,
      0.0,
      0.0,
      0.0,
      41.2452126,
      0.004785653,
      0.218511939,
      0.000706231338,
      0.0267099179,
      0.004384478,
      0.01351079
    ]
  }
]