{
  "$type": "miHoYo.HYG.Performance.PerformanceGraph, Assembly-CSharp",
  "id": 21000120072,
  "maxVoiceIdIndex": 1,
  "maxTextMapIdIndex": 1,
  "name": "日常对话-日常闲聊-单一闲聊-有条件-NPC自身-对自己服装的评价-12绵朵莉",
  "kmPageId": 333096,
  "kmEncId": "mh2kh1idhn78",
  "sheetName": "单一闲聊",
  "editRootPos": {
    "x": 0.0,
    "y": 0.0,
    "z": 0.0
  },
  "editRootRot": {
    "x": 0.0,
    "y": 0.0,
    "z": 0.0,
    "w": 0.0
  },
  "overrideGraphCfg": true,
  "graphCfgId": 0,
  "castDic": {
    "$type": "System.Collections.Generic.Dictionary`2[[System.String, mscorlib],[System.Int32, mscorlib]], mscorlib"
  },
  "editorEntityCast": {
    "$type": "System.Collections.Generic.Dictionary`2[[System.String, mscorlib],[System.UInt64, mscorlib]], mscorlib"
  },
  "paramDic": {
    "$type": "System.Collections.Generic.Dictionary`2[[System.String, mscorlib],[System.Int32, mscorlib]], mscorlib"
  },
  "effectDic": {
    "$type": "System.Collections.Generic.Dictionary`2[[System.String, mscorlib],[miHoYo.HYG.Performance.DialogEffectCfg, Assembly-CSharp]], mscorlib"
  },
  "performRoot": {
    "$type": "miHoYo.HYG.StaticPosition, Assembly-CSharp",
    "xPos": 0.0,
    "yPos": 0.0,
    "zPos": 0.0,
    "yAngle": 0.0,
    "galaxyPositionInfo": null
  },
  "blackboardConfigs": {
    "$type": "miHoYo.HYG.DataSharing.BlackboardConfigPicker, Assembly-CSharp",
    "paraKeys": null,
    "configs": null,
    "noSharingKeys": null
  },
  "castDic_edit": {
    "$type": "System.Collections.Generic.List`1[[miHoYo.HYG.Performance.StringIntPair, Assembly-CSharp]], mscorlib",
    "$values": []
  },
  "editorEntityCast_edit": {
    "$type": "System.Collections.Generic.List`1[[miHoYo.HYG.Performance.EditorGuidPair, Assembly-CSharp]], mscorlib",
    "$values": []
  },
  "timbreDatas_edit": {
    "$type": "System.Collections.Generic.List`1[[miHoYo.HYG.Performance.TimbreDataPair, Assembly-CSharp]], mscorlib",
    "$values": []
  },
  "paramDic_edit": {
    "$type": "System.Collections.Generic.List`1[[miHoYo.HYG.Performance.StringIntPair, Assembly-CSharp]], mscorlib",
    "$values": []
  },
  "effectDic_edit": {
    "$type": "System.Collections.Generic.List`1[[miHoYo.HYG.Performance.StringEffectPair, Assembly-CSharp]], mscorlib",
    "$values": []
  },
  "kmInfo_edit": {
    "$type": "System.Collections.Generic.List`1[[miHoYo.HYG.Performance.DynamicKMInfoPair, Assembly-CSharp]], mscorlib",
    "$values": []
  },
  "selectItem_count": 0,
  "textNodeMaxIndex": 7,
  "nodeMaxIndex": 11,
  "testGMGroup": "",
  "desc": null,
  "NewNodesPlaceholder": {
    "$type": "miHoYo.HYG.Performance.CfgPerformanceNode[], Assembly-CSharp",
    "$values": [
      {
        "$type": "miHoYo.HYG.Performance.CfgNextSelector, Assembly-CSharp",
        "selectors": {
          "$type": "System.Collections.Generic.List`1[[miHoYo.HYG.SelectorItem, Assembly-CSharp]], mscorlib",
          "$values": [
            {
              "$type": "miHoYo.HYG.SelectorItem, Assembly-CSharp",
              "id": 0,
              "conditionWrapper": {
                "$type": "miHoYo.HYG.SelectorCondition, Assembly-CSharp",
                "desc": "特别喜欢",
                "condition": null
              },
              "isExclusive": false,
              "exclusivePossibility": 100,
              "useConfigVarWeight": false,
              "weight": 1.0,
              "configVarWeight": null,
              "record": false,
              "memoryStrKey": null,
              "memoryKey": 0,
              "deltaWeight": 0.0
            },
            {
              "$type": "miHoYo.HYG.SelectorItem, Assembly-CSharp",
              "id": 0,
              "conditionWrapper": {
                "$type": "miHoYo.HYG.SelectorCondition, Assembly-CSharp",
                "desc": "喜欢",
                "condition": null
              },
              "isExclusive": false,
              "exclusivePossibility": 100,
              "useConfigVarWeight": false,
              "weight": 1.0,
              "configVarWeight": null,
              "record": false,
              "memoryStrKey": null,
              "memoryKey": 0,
              "deltaWeight": 0.0
            },
            {
              "$type": "miHoYo.HYG.SelectorItem, Assembly-CSharp",
              "id": 0,
              "conditionWrapper": {
                "$type": "miHoYo.HYG.SelectorCondition, Assembly-CSharp",
                "desc": "一般",
                "condition": null
              },
              "isExclusive": false,
              "exclusivePossibility": 100,
              "useConfigVarWeight": false,
              "weight": 1.0,
              "configVarWeight": null,
              "record": false,
              "memoryStrKey": null,
              "memoryKey": 0,
              "deltaWeight": 0.0
            }
          ]
        },
        "needCache": true,
        "_branches": {
          "$type": "System.Int32[], mscorlib",
          "$values": [
            1,
            2,
            3
          ]
        },
        "nodeId": 1,
        "index": 0,
        "parentIndex": -1,
        "Guid": "9c8a5293-4641-4872-b465-ef8573917d99"
      },
      {
        "$type": "miHoYo.HYG.Performance.CfgNextSelector, Assembly-CSharp",
        "selectors": {
          "$type": "System.Collections.Generic.List`1[[miHoYo.HYG.SelectorItem, Assembly-CSharp]], mscorlib",
          "$values": [
            {
              "$type": "miHoYo.HYG.SelectorItem, Assembly-CSharp",
              "id": 0,
              "conditionWrapper": {
                "$type": "miHoYo.HYG.SelectorCondition, Assembly-CSharp",
                "desc": null,
                "condition": null
              },
              "isExclusive": false,
              "exclusivePossibility": 100,
              "useConfigVarWeight": false,
              "weight": 1.0,
              "configVarWeight": null,
              "record": false,
              "memoryStrKey": null,
              "memoryKey": 0,
              "deltaWeight": 0.0
            }
          ]
        },
        "needCache": false,
        "_branches": {
          "$type": "System.Int32[], mscorlib",
          "$values": [
            4
          ]
        },
        "nodeId": 2,
        "index": 1,
        "parentIndex": 0,
        "Guid": "141fb852-e833-4bcc-b47b-743522446da1"
      },
      {
        "$type": "miHoYo.HYG.Performance.CfgNextSelector, Assembly-CSharp",
        "selectors": {
          "$type": "System.Collections.Generic.List`1[[miHoYo.HYG.SelectorItem, Assembly-CSharp]], mscorlib",
          "$values": [
            {
              "$type": "miHoYo.HYG.SelectorItem, Assembly-CSharp",
              "id": 0,
              "conditionWrapper": {
                "$type": "miHoYo.HYG.SelectorCondition, Assembly-CSharp",
                "desc": null,
                "condition": null
              },
              "isExclusive": false,
              "exclusivePossibility": 100,
              "useConfigVarWeight": false,
              "weight": 1.0,
              "configVarWeight": null,
              "record": false,
              "memoryStrKey": null,
              "memoryKey": 0,
              "deltaWeight": 0.0
            },
            {
              "$type": "miHoYo.HYG.SelectorItem, Assembly-CSharp",
              "id": 0,
              "conditionWrapper": {
                "$type": "miHoYo.HYG.SelectorCondition, Assembly-CSharp",
                "desc": null,
                "condition": null
              },
              "isExclusive": false,
              "exclusivePossibility": 100,
              "useConfigVarWeight": false,
              "weight": 1.0,
              "configVarWeight": null,
              "record": false,
              "memoryStrKey": null,
              "memoryKey": 0,
              "deltaWeight": 0.0
            },
            {
              "$type": "miHoYo.HYG.SelectorItem, Assembly-CSharp",
              "id": 0,
              "conditionWrapper": {
                "$type": "miHoYo.HYG.SelectorCondition, Assembly-CSharp",
                "desc": null,
                "condition": null
              },
              "isExclusive": false,
              "exclusivePossibility": 100,
              "useConfigVarWeight": false,
              "weight": 1.0,
              "configVarWeight": null,
              "record": false,
              "memoryStrKey": null,
              "memoryKey": 0,
              "deltaWeight": 0.0
            }
          ]
        },
        "needCache": false,
        "_branches": {
          "$type": "System.Int32[], mscorlib",
          "$values": [
            5,
            6,
            7
          ]
        },
        "nodeId": 3,
        "index": 2,
        "parentIndex": 0,
        "Guid": "e226691f-19be-4281-a2b0-4d9a36516e2c"
      },
      {
        "$type": "miHoYo.HYG.Performance.CfgNextSelector, Assembly-CSharp",
        "selectors": {
          "$type": "System.Collections.Generic.List`1[[miHoYo.HYG.SelectorItem, Assembly-CSharp]], mscorlib",
          "$values": [
            {
              "$type": "miHoYo.HYG.SelectorItem, Assembly-CSharp",
              "id": 0,
              "conditionWrapper": {
                "$type": "miHoYo.HYG.SelectorCondition, Assembly-CSharp",
                "desc": null,
                "condition": null
              },
              "isExclusive": false,
              "exclusivePossibility": 100,
              "useConfigVarWeight": false,
              "weight": 1.0,
              "configVarWeight": null,
              "record": false,
              "memoryStrKey": null,
              "memoryKey": 0,
              "deltaWeight": 0.0
            },
            {
              "$type": "miHoYo.HYG.SelectorItem, Assembly-CSharp",
              "id": 0,
              "conditionWrapper": {
                "$type": "miHoYo.HYG.SelectorCondition, Assembly-CSharp",
                "desc": null,
                "condition": null
              },
              "isExclusive": false,
              "exclusivePossibility": 100,
              "useConfigVarWeight": false,
              "weight": 1.0,
              "configVarWeight": null,
              "record": false,
              "memoryStrKey": null,
              "memoryKey": 0,
              "deltaWeight": 0.0
            }
          ]
        },
        "needCache": false,
        "_branches": {
          "$type": "System.Int32[], mscorlib",
          "$values": [
            8,
            9
          ]
        },
        "nodeId": 4,
        "index": 3,
        "parentIndex": 0,
        "Guid": "3c24743c-785c-4f61-8050-d4581d4dc065"
      },
      {
        "$type": "miHoYo.HYG.Performance.CfgDialogGroup, Assembly-CSharp",
        "desc": null,
        "textMaxIndex": 0,
        "textGroupId": "20000000072_1",
        "useFixedDialogGroup": false,
        "fixedDialogGroupId": 0,
        "dialogs": {
          "$type": "System.Collections.Generic.List`1[[miHoYo.HYG.Performance.DialogCfg, Assembly-CSharp]], mscorlib",
          "$values": [
            {
              "$type": "miHoYo.HYG.Performance.DialogCfg, Assembly-CSharp",
              "textId": 0,
              "pTimelineId": "",
              "speakerKey": "PerformTrigger",
              "voiceId": "",
              "fakeName": null,
              "fakeName_l10n": {
                "$type": "miHoYo.HYG.Localization.LocalizationString, Assembly-Common",
                "textId": "Performance_21000120072_38295_fakeName",
                "value": null
              },
              "content": "身上的这件……\n是我喜欢的天空颜色的衣服！\n穿起来，就像融入天空的小云朵。",
              "content_l10n": {
                "$type": "miHoYo.HYG.Localization.LocalizationString, Assembly-Common",
                "textId": "Performance_21000120072_38295_content",
                "value": "身上的这件……\n是我喜欢的天空颜色的衣服！\n穿起来，就像融入天空的小云朵。"
              },
              "nextRule": 0,
              "guardPeriod": 0.0,
              "desc": null,
              "voiceText": null,
              "expressiveDesc": null,
              "textGuid": 38295
            },
            {
              "$type": "miHoYo.HYG.Performance.DialogCfg, Assembly-CSharp",
              "textId": 0,
              "pTimelineId": "",
              "speakerKey": "PerformTrigger",
              "voiceId": "",
              "fakeName": null,
              "fakeName_l10n": {
                "$type": "miHoYo.HYG.Localization.LocalizationString, Assembly-Common",
                "textId": "Performance_21000120072_38296_fakeName",
                "value": null
              },
              "content": "{A笑眯眯}蓝天白云虽然只是四个字……\n但穿在身上，\n让我想起记忆里、一张又一张、不同的画。",
              "content_l10n": {
                "$type": "miHoYo.HYG.Localization.LocalizationString, Assembly-Common",
                "textId": "Performance_21000120072_38296_content",
                "value": "{A笑眯眯}蓝天白云虽然只是四个字……\n但穿在身上，\n让我想起记忆里、一张又一张、不同的画。"
              },
              "nextRule": 0,
              "guardPeriod": 0.0,
              "desc": null,
              "voiceText": null,
              "expressiveDesc": null,
              "textGuid": 38296
            }
          ]
        },
        "banPT": false,
        "positionInfo": null,
        "_output": -1,
        "nodeId": 5,
        "index": 4,
        "parentIndex": 1,
        "Guid": "275baea5-a2a8-46a7-b4a0-9bb7332df835"
      },
      {
        "$type": "miHoYo.HYG.Performance.CfgDialogGroup, Assembly-CSharp",
        "desc": null,
        "textMaxIndex": 0,
        "textGroupId": "20000000072_2",
        "useFixedDialogGroup": false,
        "fixedDialogGroupId": 0,
        "dialogs": {
          "$type": "System.Collections.Generic.List`1[[miHoYo.HYG.Performance.DialogCfg, Assembly-CSharp]], mscorlib",
          "$values": [
            {
              "$type": "miHoYo.HYG.Performance.DialogCfg, Assembly-CSharp",
              "textId": 0,
              "pTimelineId": "",
              "speakerKey": "PerformTrigger",
              "voiceId": "",
              "fakeName": null,
              "fakeName_l10n": {
                "$type": "miHoYo.HYG.Localization.LocalizationString, Assembly-Common",
                "textId": "Performance_21000120072_38297_fakeName",
                "value": null
              },
              "content": "身上的这件……\n是我喜欢的天空颜色的衣服！\n穿起来，就像融入天空的小云朵。",
              "content_l10n": {
                "$type": "miHoYo.HYG.Localization.LocalizationString, Assembly-Common",
                "textId": "Performance_21000120072_38297_content",
                "value": "身上的这件……\n是我喜欢的天空颜色的衣服！\n穿起来，就像融入天空的小云朵。"
              },
              "nextRule": 0,
              "guardPeriod": 0.0,
              "desc": null,
              "voiceText": null,
              "expressiveDesc": null,
              "textGuid": 38297
            },
            {
              "$type": "miHoYo.HYG.Performance.DialogCfg, Assembly-CSharp",
              "textId": 0,
              "pTimelineId": "",
              "speakerKey": "PerformTrigger",
              "voiceId": "",
              "fakeName": null,
              "fakeName_l10n": {
                "$type": "miHoYo.HYG.Localization.LocalizationString, Assembly-Common",
                "textId": "Performance_21000120072_38298_fakeName",
                "value": null
              },
              "content": "{A笑眯眯}蓝天白云虽然只是四个字……\n但对我来说，\n是一张又一张、记忆里、不同的画。",
              "content_l10n": {
                "$type": "miHoYo.HYG.Localization.LocalizationString, Assembly-Common",
                "textId": "Performance_21000120072_38298_content",
                "value": "{A笑眯眯}蓝天白云虽然只是四个字……\n但对我来说，\n是一张又一张、记忆里、不同的画。"
              },
              "nextRule": 0,
              "guardPeriod": 0.0,
              "desc": null,
              "voiceText": null,
              "expressiveDesc": null,
              "textGuid": 38298
            }
          ]
        },
        "banPT": false,
        "positionInfo": null,
        "_output": -1,
        "nodeId": 6,
        "index": 5,
        "parentIndex": 2,
        "Guid": "1cc97a9d-6040-429e-ba09-968a9f85f4ae"
      },
      {
        "$type": "miHoYo.HYG.Performance.CfgDialogGroup, Assembly-CSharp",
        "desc": null,
        "textMaxIndex": 0,
        "textGroupId": "20000000072_3",
        "useFixedDialogGroup": false,
        "fixedDialogGroupId": 0,
        "dialogs": {
          "$type": "System.Collections.Generic.List`1[[miHoYo.HYG.Performance.DialogCfg, Assembly-CSharp]], mscorlib",
          "$values": [
            {
              "$type": "miHoYo.HYG.Performance.DialogCfg, Assembly-CSharp",
              "textId": 0,
              "pTimelineId": "",
              "speakerKey": "PerformTrigger",
              "voiceId": "",
              "fakeName": null,
              "fakeName_l10n": {
                "$type": "miHoYo.HYG.Localization.LocalizationString, Assembly-Common",
                "textId": "Performance_21000120072_38299_fakeName",
                "value": null
              },
              "content": "身上的这件……\n是我喜欢的天空颜色的衣服！\n穿起来，就像融入天空的小云朵。",
              "content_l10n": {
                "$type": "miHoYo.HYG.Localization.LocalizationString, Assembly-Common",
                "textId": "Performance_21000120072_38299_content",
                "value": "身上的这件……\n是我喜欢的天空颜色的衣服！\n穿起来，就像融入天空的小云朵。"
              },
              "nextRule": 0,
              "guardPeriod": 0.0,
              "desc": null,
              "voiceText": null,
              "expressiveDesc": null,
              "textGuid": 38299
            },
            {
              "$type": "miHoYo.HYG.Performance.DialogCfg, Assembly-CSharp",
              "textId": 0,
              "pTimelineId": "",
              "speakerKey": "PerformTrigger",
              "voiceId": "",
              "fakeName": null,
              "fakeName_l10n": {
                "$type": "miHoYo.HYG.Localization.LocalizationString, Assembly-Common",
                "textId": "Performance_21000120072_38300_fakeName",
                "value": null
              },
              "content": "{A笑眯眯}蓝天白云虽然只是四个字……\n但对我来说，\n是一张又一张、记忆里、不同的画。",
              "content_l10n": {
                "$type": "miHoYo.HYG.Localization.LocalizationString, Assembly-Common",
                "textId": "Performance_21000120072_38300_content",
                "value": "{A笑眯眯}蓝天白云虽然只是四个字……\n但对我来说，\n是一张又一张、记忆里、不同的画。"
              },
              "nextRule": 0,
              "guardPeriod": 0.0,
              "desc": null,
              "voiceText": null,
              "expressiveDesc": null,
              "textGuid": 38300
            }
          ]
        },
        "banPT": false,
        "positionInfo": null,
        "_output": -1,
        "nodeId": 7,
        "index": 6,
        "parentIndex": 2,
        "Guid": "c601c7f2-552b-4fa2-8407-1049556661df"
      },
      {
        "$type": "miHoYo.HYG.Performance.CfgDialogGroup, Assembly-CSharp",
        "desc": null,
        "textMaxIndex": 0,
        "textGroupId": "20000000072_4",
        "useFixedDialogGroup": false,
        "fixedDialogGroupId": 0,
        "dialogs": {
          "$type": "System.Collections.Generic.List`1[[miHoYo.HYG.Performance.DialogCfg, Assembly-CSharp]], mscorlib",
          "$values": [
            {
              "$type": "miHoYo.HYG.Performance.DialogCfg, Assembly-CSharp",
              "textId": 0,
              "pTimelineId": "",
              "speakerKey": "PerformTrigger",
              "voiceId": "",
              "fakeName": null,
              "fakeName_l10n": {
                "$type": "miHoYo.HYG.Localization.LocalizationString, Assembly-Common",
                "textId": "Performance_21000120072_38301_fakeName",
                "value": null
              },
              "content": "我喜欢宽松舒适、软咩咩的衣服，\n那让我在紧张的时候保持松弛，\n散步，或是咩玩偶……都很舒适呐！",
              "content_l10n": {
                "$type": "miHoYo.HYG.Localization.LocalizationString, Assembly-Common",
                "textId": "Performance_21000120072_38301_content",
                "value": "我喜欢宽松舒适、软咩咩的衣服，\n那让我在紧张的时候保持松弛，\n散步，或是咩玩偶……都很舒适呐！"
              },
              "nextRule": 0,
              "guardPeriod": 0.0,
              "desc": null,
              "voiceText": null,
              "expressiveDesc": null,
              "textGuid": 38301
            },
            {
              "$type": "miHoYo.HYG.Performance.DialogCfg, Assembly-CSharp",
              "textId": 0,
              "pTimelineId": "",
              "speakerKey": "PerformTrigger",
              "voiceId": "",
              "fakeName": null,
              "fakeName_l10n": {
                "$type": "miHoYo.HYG.Localization.LocalizationString, Assembly-Common",
                "textId": "Performance_21000120072_38302_fakeName",
                "value": null
              },
              "content": "{A观察地面}穿上以后，\n像被温柔的世界，包裹着一样。",
              "content_l10n": {
                "$type": "miHoYo.HYG.Localization.LocalizationString, Assembly-Common",
                "textId": "Performance_21000120072_38302_content",
                "value": "{A观察地面}穿上以后，\n像被温柔的世界，包裹着一样。"
              },
              "nextRule": 0,
              "guardPeriod": 0.0,
              "desc": null,
              "voiceText": null,
              "expressiveDesc": null,
              "textGuid": 38302
            }
          ]
        },
        "banPT": false,
        "positionInfo": null,
        "_output": -1,
        "nodeId": 8,
        "index": 7,
        "parentIndex": 2,
        "Guid": "93977c50-742b-4b5b-b565-48a6b59a5361"
      },
      {
        "$type": "miHoYo.HYG.Performance.CfgDialogGroup, Assembly-CSharp",
        "desc": null,
        "textMaxIndex": 0,
        "textGroupId": "20000000072_5",
        "useFixedDialogGroup": false,
        "fixedDialogGroupId": 0,
        "dialogs": {
          "$type": "System.Collections.Generic.List`1[[miHoYo.HYG.Performance.DialogCfg, Assembly-CSharp]], mscorlib",
          "$values": [
            {
              "$type": "miHoYo.HYG.Performance.DialogCfg, Assembly-CSharp",
              "textId": 0,
              "pTimelineId": "",
              "speakerKey": "PerformTrigger",
              "voiceId": "",
              "fakeName": null,
              "fakeName_l10n": {
                "$type": "miHoYo.HYG.Localization.LocalizationString, Assembly-Common",
                "textId": "Performance_21000120072_38303_fakeName",
                "value": null
              },
              "content": "身上穿的服装是我精挑细选的，\n是适合日常的舒适便捷的衣服。",
              "content_l10n": {
                "$type": "miHoYo.HYG.Localization.LocalizationString, Assembly-Common",
                "textId": "Performance_21000120072_38303_content",
                "value": "身上穿的服装是我精挑细选的，\n是适合日常的舒适便捷的衣服。"
              },
              "nextRule": 0,
              "guardPeriod": 0.0,
              "desc": null,
              "voiceText": null,
              "expressiveDesc": null,
              "textGuid": 38303
            }
          ]
        },
        "banPT": false,
        "positionInfo": null,
        "_output": -1,
        "nodeId": 9,
        "index": 8,
        "parentIndex": 3,
        "Guid": "0044dc1f-c9f5-4a04-a79b-1f033389eaec"
      },
      {
        "$type": "miHoYo.HYG.Performance.CfgDialogGroup, Assembly-CSharp",
        "desc": null,
        "textMaxIndex": 0,
        "textGroupId": "20000000072_6",
        "useFixedDialogGroup": false,
        "fixedDialogGroupId": 0,
        "dialogs": {
          "$type": "System.Collections.Generic.List`1[[miHoYo.HYG.Performance.DialogCfg, Assembly-CSharp]], mscorlib",
          "$values": []
        },
        "banPT": false,
        "positionInfo": null,
        "_output": -1,
        "nodeId": 10,
        "index": 9,
        "parentIndex": 3,
        "Guid": "51f25bbb-2422-4ece-a29e-816812fbf4ab"
      }
    ]
  },
  "containers": null,
  "rootIndex": 0,
  "nodesHash": 747871464,
  "editorData": {
    "$type": "miHoYo.HYG.JsonGraph.GraphEditorData, Assembly-CSharp",
    "danglingIndexes": {
      "$type": "System.Int32[], mscorlib",
      "$values": []
    },
    "nodeInfos": {
      "$type": "System.Collections.Generic.List`1[[miHoYo.HYG.JsonGraph.NodeEditorData, Assembly-CSharp]], mscorlib",
      "$values": [
        {
          "$type": "miHoYo.HYG.JsonGraph.NodeEditorData, Assembly-CSharp",
          "pos": {
            "x": -322.0,
            "y": -47.5
          },
          "guid": "9c8a5293-4641-4872-b465-ef8573917d99",
          "comment": null,
          "locked": false,
          "collapse": false
        },
        {
          "$type": "miHoYo.HYG.JsonGraph.NodeEditorData, Assembly-CSharp",
          "pos": {
            "x": 240.0,
            "y": -384.0
          },
          "guid": "141fb852-e833-4bcc-b47b-743522446da1",
          "comment": null,
          "locked": false,
          "collapse": false
        },
        {
          "$type": "miHoYo.HYG.JsonGraph.NodeEditorData, Assembly-CSharp",
          "pos": {
            "x": 240.0,
            "y": -32.0
          },
          "guid": "e226691f-19be-4281-a2b0-4d9a36516e2c",
          "comment": null,
          "locked": false,
          "collapse": false
        },
        {
          "$type": "miHoYo.HYG.JsonGraph.NodeEditorData, Assembly-CSharp",
          "pos": {
            "x": 240.0,
            "y": 672.0
          },
          "guid": "3c24743c-785c-4f61-8050-d4581d4dc065",
          "comment": null,
          "locked": false,
          "collapse": false
        },
        {
          "$type": "miHoYo.HYG.JsonGraph.NodeEditorData, Assembly-CSharp",
          "pos": {
            "x": 832.0,
            "y": -384.0
          },
          "guid": "275baea5-a2a8-46a7-b4a0-9bb7332df835",
          "comment": "",
          "locked": false,
          "collapse": false
        },
        {
          "$type": "miHoYo.HYG.JsonGraph.NodeEditorData, Assembly-CSharp",
          "pos": {
            "x": 832.0,
            "y": -32.0
          },
          "guid": "1cc97a9d-6040-429e-ba09-968a9f85f4ae",
          "comment": "",
          "locked": false,
          "collapse": false
        },
        {
          "$type": "miHoYo.HYG.JsonGraph.NodeEditorData, Assembly-CSharp",
          "pos": {
            "x": 832.0,
            "y": 160.0
          },
          "guid": "c601c7f2-552b-4fa2-8407-1049556661df",
          "comment": "",
          "locked": false,
          "collapse": false
        },
        {
          "$type": "miHoYo.HYG.JsonGraph.NodeEditorData, Assembly-CSharp",
          "pos": {
            "x": 832.0,
            "y": 368.0
          },
          "guid": "93977c50-742b-4b5b-b565-48a6b59a5361",
          "comment": "",
          "locked": false,
          "collapse": false
        },
        {
          "$type": "miHoYo.HYG.JsonGraph.NodeEditorData, Assembly-CSharp",
          "pos": {
            "x": 816.0,
            "y": 688.0
          },
          "guid": "0044dc1f-c9f5-4a04-a79b-1f033389eaec",
          "comment": "",
          "locked": false,
          "collapse": false
        },
        {
          "$type": "miHoYo.HYG.JsonGraph.NodeEditorData, Assembly-CSharp",
          "pos": {
            "x": 816.0,
            "y": 896.0
          },
          "guid": "51f25bbb-2422-4ece-a29e-816812fbf4ab",
          "comment": "",
          "locked": false,
          "collapse": false
        }
      ]
    },
    "comment": null
  },
  "path": "Assets/MoleRes/Rel/SRes/Data/Json/Performance/21000120072.json",
  "errors": null,
  "nodeErrors": null
}